{"players":[{"name":"Toliam","region":"euw1","matches":[{"champ":"Shaco","patch":"9.2.","date":1549225233230,"enemy Team":["Darius","LeBlanc","Viktor","Taric","Graves"],"ally Team":["Ezreal","Cassiopeia","Shaco","Urgot","Zyra"],"mastery 1":"Fleet Footwork","mastery 2":"Triumph","mastery 3":"Legend: Alacrity","mastery 4":"Coup de Grace","mastery 5":"Absolute Focus","mastery 6":"Waterwalking","max":["E","Q","W"],"skill Order":["W","Q","E","Q","Q","R","E","E","E","E","R","Q","Q","W","W","R","W"],"victory":false,"blue Side":false,"summ Spell 1":"Ignite","summ Spell 2":"Smite","kda":{"kills":10,"deaths":3,"assists":10},"ccDealt":1208,"wardsKilled":4,"wardsPlaced":13,"csPerMinAt20Mins":1},{"champ":"Urgot","patch":"9.1.","date":1547334321795,"enemy Team":["Gnar","Evelynn","Pyke","Caitlyn","Lissandra"],"ally Team":["Corki","Urgot","Alistar","Riven","Kalista"],"mastery 1":"Unsealed Spellbook","mastery 2":"Magical Footwear","mastery 3":"Minion Dematerializer","mastery 4":"Time Warp Tonic","mastery 5":8401,"mastery 6":"Bone Plating","max":["Q"],"skill Order":["Q","W","E","Q","Q","R","Q","W","Q","E","R","W"],"victory":true,"blue Side":true,"summ Spell 1":"Flash","summ Spell 2":"Teleport","kda":{"kills":7,"deaths":3,"assists":3},"ccDealt":191,"wardsKilled":4,"wardsPlaced":8,"csPerMinAt20Mins":6.8},{"champ":"Jax","patch":"8.24","date":1546362880557,"enemy Team":["Kai'sa","Thresh","Irelia","Xin Zhao","Riven"],"ally Team":["Vayne","Braum","Jax","Yasuo","Evelynn"],"mastery 1":"Conqueror","mastery 2":"Triumph","mastery 3":"Legend: Alacrity","mastery 4":"Coup de Grace","mastery 5":"Sudden Impact","mastery 6":"Ghost Poro","max":["W","Q"],"skill Order":["E","Q","W","W","W","R","W","Q","W","Q","R","Q","Q","E","E"],"victory":false,"blue Side":true,"summ Spell 1":"Flash","summ Spell 2":"Teleport","kda":{"kills":3,"deaths":7,"assists":3},"ccDealt":57,"wardsKilled":1,"wardsPlaced":8,"csPerMinAt20Mins":8.3},{"champ":"Jax","patch":"8.24","date":1546321256085,"enemy Team":["Lucian","Rengar","Fizz","Darius","Nami"],"ally Team":["Xin Zhao","Jax","Poppy","Vladimir","Miss Fortune"],"mastery 1":"Conqueror","mastery 2":"Triumph","mastery 3":"Legend: Alacrity","mastery 4":"Last Stand","mastery 5":"Sudden Impact","mastery 6":"Ravenous Hunter","max":["W","Q","E"],"skill Order":["E","Q","W","W","W","R","W","Q","W","Q","R","Q","Q","E","E","R","E"],"victory":true,"blue Side":false,"summ Spell 1":"Flash","summ Spell 2":"Teleport","kda":{"kills":16,"deaths":4,"assists":3},"ccDealt":153,"wardsKilled":3,"wardsPlaced":11,"csPerMinAt20Mins":6.449999999999999},{"champ":"Heimerdinger","patch":"8.24","date":1546190373139,"enemy Team":["Nasus","Kai'sa","Galio","Karma","Xin Zhao"],"ally Team":["Corki","Heimerdinger","Volibear","Fiora","Gragas"],"mastery 1":"Summon Aery","mastery 2":"Manaflow Band","mastery 3":"Absolute Focus","mastery 4":"Scorch","mastery 5":"Eyeball Collection","mastery 6":"Ravenous Hunter","max":["W","Q"],"skill Order":["Q","E","W","W","W","R","W","Q","W","Q","R","Q","Q","E"],"victory":true,"blue Side":true,"summ Spell 1":"Flash","summ Spell 2":"Teleport","kda":{"kills":4,"deaths":1,"assists":7},"ccDealt":239,"wardsKilled":2,"wardsPlaced":10,"csPerMinAt20Mins":6.6},{"champ":"Heimerdinger","patch":"8.24","date":1544111443833,"enemy Team":["Lee Sin","Neeko","Morgana","Talon","Xayah"],"ally Team":["Heimerdinger","Zed","Jhin","Alistar","Fiddlesticks"],"mastery 1":"Dark Harvest","mastery 2":"Taste of Blood","mastery 3":"Eyeball Collection","mastery 4":"Ravenous Hunter","mastery 5":"Manaflow Band","mastery 6":"Absolute Focus","max":["W","Q"],"skill Order":["Q","E","W","W","W","R","W","Q","W","Q","R","Q","Q","E","E","R"],"victory":false,"blue Side":false,"summ Spell 1":"Flash","summ Spell 2":"Teleport","kda":{"kills":6,"deaths":6,"assists":8},"ccDealt":197,"wardsKilled":7,"wardsPlaced":9,"csPerMinAt20Mins":6.75},{"champ":"Illaoi","patch":"8.22","date":1542127185055,"enemy Team":["Pyke","Ezreal","Twitch","Fiora","LeBlanc"],"ally Team":["Fizz","Aatrox","Illaoi","Kai'sa","Rakan"],"mastery 1":"Kleptomancy","mastery 2":"Magical Footwear","mastery 3":"Biscuit Delivery","mastery 4":"Time Warp Tonic","mastery 5":"Revitalize","mastery 6":"Bone Plating","max":["Q","E"],"skill Order":["Q","W","E","Q","Q","R","Q","E","Q","E","R","E","E","W","W"],"victory":true,"blue Side":false,"summ Spell 1":"Flash","summ Spell 2":"Teleport","kda":{"kills":4,"deaths":4,"assists":1},"ccDealt":25,"wardsKilled":2,"wardsPlaced":10,"csPerMinAt20Mins":8.3},{"champ":"Illaoi","patch":"8.22","date":1542030241725,"enemy Team":["Maokai","Kai'sa","Thresh","Ryze","Nocturne"],"ally Team":["Camille","Talon","Illaoi","Xayah","Alistar"],"mastery 1":"Kleptomancy","mastery 2":"Magical Footwear","mastery 3":"Biscuit Delivery","mastery 4":"Time Warp Tonic","mastery 5":"Bone Plating","mastery 6":"Revitalize","max":["Q","E"],"skill Order":["Q","W","E","Q","Q","R","Q","E","Q","E","R","E","E","W"],"victory":true,"blue Side":false,"summ Spell 1":"Flash","summ Spell 2":"Teleport","kda":{"kills":2,"deaths":4,"assists":1},"ccDealt":85,"wardsKilled":0,"wardsPlaced":15,"csPerMinAt20Mins":8.350000000000001},{"champ":"Tryndamere","patch":"8.22","date":1542027884960,"enemy Team":["Kai'sa","Alistar","Jax","Malzahar","Ekko"],"ally Team":["Thresh","Lucian","Tryndamere","Kha'Zix","Katarina"],"mastery 1":"Conqueror","mastery 2":"Triumph","mastery 3":"Legend: Alacrity","mastery 4":"Last Stand","mastery 5":"Bone Plating","mastery 6":"Revitalize","max":["Q","E","W"],"skill Order":["E","Q","Q","W","Q","R","Q","E","Q","E","E","E","W","W","W","W","R","R"],"victory":true,"blue Side":true,"summ Spell 1":"Flash","summ Spell 2":"Teleport","kda":{"kills":9,"deaths":2,"assists":10},"ccDealt":356,"wardsKilled":8,"wardsPlaced":7,"csPerMinAt20Mins":9.149999999999999},{"champ":"Heimerdinger","patch":"8.22","date":1541986727309,"enemy Team":["Viktor","Lucian","Kha'Zix","Fiddlesticks","Kassadin"],"ally Team":["Xayah","Rakan","Lux","Graves","Heimerdinger"],"mastery 1":"Summon Aery","mastery 2":"Manaflow Band","mastery 3":"Absolute Focus","mastery 4":"Scorch","mastery 5":"Minion Dematerializer","mastery 6":"Time Warp Tonic","max":["W","Q"],"skill Order":["Q","E","W","W","W","R","W","Q","Q","W","R","Q","Q","E","E"],"victory":false,"blue Side":true,"summ Spell 1":"Flash","summ Spell 2":"Teleport","kda":{"kills":2,"deaths":4,"assists":4},"ccDealt":148,"wardsKilled":3,"wardsPlaced":14,"csPerMinAt20Mins":8.55},{"champ":"Illaoi","patch":"8.22","date":1541984699276,"enemy Team":["Rakan","Xayah","Karma","Olaf","Sion"],"ally Team":["Pyke","Lucian","Braum","Gragas","Illaoi"],"mastery 1":"Kleptomancy","mastery 2":"Magical Footwear","mastery 3":"Biscuit Delivery","mastery 4":"Time Warp Tonic","mastery 5":"Bone Plating","mastery 6":"Revitalize","max":["Q","E"],"skill Order":["Q","W","E","Q","Q","R","Q","E","Q","E","R","E","E","W"],"victory":false,"blue Side":false,"summ Spell 1":"Flash","summ Spell 2":"Teleport","kda":{"kills":1,"deaths":3,"assists":2},"ccDealt":28,"wardsKilled":3,"wardsPlaced":11,"csPerMinAt20Mins":8.2},{"champ":"Singed","patch":"8.22","date":1541982211606,"enemy Team":["Graves","Pyke","Ashe","Aatrox","Riven"],"ally Team":["Lux","Draven","Taliyah","Thresh","Singed"],"mastery 1":"Unsealed Spellbook","mastery 2":"Magical Footwear","mastery 3":"Future's Market","mastery 4":"Time Warp Tonic","mastery 5":"Chrysalis","mastery 6":"Bone Plating","max":["Q","E","W"],"skill Order":["Q","E","Q","W","Q","R","Q","E","Q","E","R","E","E","W","W","R","W"],"victory":true,"blue Side":false,"summ Spell 1":"Flash","summ Spell 2":"Ignite","kda":{"kills":5,"deaths":6,"assists":16},"ccDealt":6427,"wardsKilled":1,"wardsPlaced":4,"csPerMinAt20Mins":7},{"champ":"Illaoi","patch":"8.22","date":1541973829556,"enemy Team":["Sivir","Jax","Kha'Zix","Alistar","Ahri"],"ally Team":["Xin Zhao","Lulu","Illaoi","Diana","Kai'sa"],"mastery 1":"Kleptomancy","mastery 2":"Magical Footwear","mastery 3":"Biscuit Delivery","mastery 4":"Time Warp Tonic","mastery 5":"Bone Plating","mastery 6":"Revitalize","max":["Q","E","W"],"skill Order":["Q","W","E","Q","Q","R","Q","E","E","Q","E","R","E","W","W","W","R","W"],"victory":false,"blue Side":false,"summ Spell 1":"Flash","summ Spell 2":"Teleport","kda":{"kills":5,"deaths":4,"assists":7},"ccDealt":172,"wardsKilled":3,"wardsPlaced":13,"csPerMinAt20Mins":9.5},{"champ":"Illaoi","patch":"8.22","date":1541966394834,"enemy Team":["Viktor","Twisted Fate","Thresh","Olaf","Lucian"],"ally Team":["Xerath","Illaoi","Xayah","Rakan","Jarvan IV"],"mastery 1":"Kleptomancy","mastery 2":"Magical Footwear","mastery 3":"Biscuit Delivery","mastery 4":"Time Warp Tonic","mastery 5":"Bone Plating","mastery 6":"Revitalize","max":["Q","E"],"skill Order":["Q","W","E","Q","Q","R","Q","E","Q","E","R","E","E","W","W","R"],"victory":true,"blue Side":true,"summ Spell 1":"Flash","summ Spell 2":"Teleport","kda":{"kills":2,"deaths":2,"assists":3},"ccDealt":22,"wardsKilled":1,"wardsPlaced":12,"csPerMinAt20Mins":7.25},{"champ":"Illaoi","patch":"8.22","date":1541894520876,"enemy Team":["Taliyah","Fiora","Lucian","Braum","Pantheon"],"ally Team":["Illaoi","Twisted Fate","Twitch","Janna","Kai'sa"],"mastery 1":"Kleptomancy","mastery 2":"Magical Footwear","mastery 3":"Biscuit Delivery","mastery 4":"Time Warp Tonic","mastery 5":"Bone Plating","mastery 6":"Revitalize","max":["Q","E"],"skill Order":["Q","W","E","Q","Q","R","Q","E","Q","E","R","E","E","W"],"victory":true,"blue Side":false,"summ Spell 1":"Flash","summ Spell 2":"Teleport","kda":{"kills":0,"deaths":3,"assists":3},"ccDealt":23,"wardsKilled":1,"wardsPlaced":9,"csPerMinAt20Mins":7.5},{"champ":"Singed","patch":"8.22","date":1541877153654,"enemy Team":["Kai'sa","Zoe","Thresh","Kha'Zix","Swain"],"ally Team":["Karma","Lucian","Camille","Singed","Orianna"],"mastery 1":"Kleptomancy","mastery 2":"Magical Footwear","mastery 3":"Biscuit Delivery","mastery 4":"Time Warp Tonic","mastery 5":"Waterwalking","mastery 6":"Shield Bash","max":["Q","E","W"],"skill Order":["Q","E","Q","W","Q","R","Q","E","Q","E","R","E","E","W","W","R","W"],"victory":false,"blue Side":true,"summ Spell 1":"Flash","summ Spell 2":"Ignite","kda":{"kills":8,"deaths":7,"assists":10},"ccDealt":8369,"wardsKilled":4,"wardsPlaced":12,"csPerMinAt20Mins":9.35},{"champ":"Singed","patch":"8.20","date":1539708125113,"enemy Team":["Cho'Gath","Viktor","Xin Zhao","Rakan","Xayah"],"ally Team":["Singed","Leona","Cassiopeia","Ezreal","Kha'Zix"],"mastery 1":"Unsealed Spellbook","mastery 2":"Magical Footwear","mastery 3":"Future's Market","mastery 4":"Time Warp Tonic","mastery 5":"Demolish","mastery 6":"Conditioning","max":["Q","E"],"skill Order":["Q","E","Q","W","Q","R","Q","E","Q","E","R","E","E","W","W","R"],"victory":true,"blue Side":false,"summ Spell 1":"Flash","summ Spell 2":"Teleport","kda":{"kills":4,"deaths":2,"assists":14},"ccDealt":3484,"wardsKilled":6,"wardsPlaced":9,"csPerMinAt20Mins":7.35},{"champ":"Singed","patch":"8.20","date":1539465790547,"enemy Team":["Janna","Kai'sa","Shaco","Camille","LeBlanc"],"ally Team":["Thresh","Rengar","Vayne","Singed","Malzahar"],"mastery 1":"Aftershock","mastery 2":"Demolish","mastery 3":"Conditioning","mastery 4":"Overgrowth","mastery 5":"Time Warp Tonic","mastery 6":"Minion Dematerializer","max":["Q","E"],"skill Order":["Q","E","W","Q","Q","R","Q","E","Q","E","R","E","E","W","W"],"victory":true,"blue Side":false,"summ Spell 1":"Flash","summ Spell 2":"Teleport","kda":{"kills":4,"deaths":1,"assists":8},"ccDealt":4260,"wardsKilled":0,"wardsPlaced":10,"csPerMinAt20Mins":7.6},{"champ":"Gangplank","patch":"8.20","date":1539462355242,"enemy Team":["Jax","Master Yi","Heimerdinger","Kai'sa","Pyke"],"ally Team":["Lux","Lee Sin","Xayah","Gangplank","Morgana"],"mastery 1":"Grasp of the Undying","mastery 2":"Demolish","mastery 3":"Chrysalis","mastery 4":"Revitalize","mastery 5":"Cosmic Insight","mastery 6":"Future's Market","max":["Q","E","W"],"skill Order":["Q","E","W","Q","Q","R","Q","E","Q","E","R","E","E","W","W","R","W","W"],"victory":false,"blue Side":true,"summ Spell 1":"Flash","summ Spell 2":"Teleport","kda":{"kills":9,"deaths":3,"assists":9},"ccDealt":1221,"wardsKilled":4,"wardsPlaced":20,"csPerMinAt20Mins":8.3},{"champ":"Singed","patch":"8.20","date":1539460239640,"enemy Team":["Taliyah","Jhin","Thresh","Fiora","Yasuo"],"ally Team":["Braum","Aatrox","Draven","Kassadin","Singed"],"mastery 1":"Aftershock","mastery 2":"Bone Plating","mastery 3":"Conditioning","mastery 4":"Unflinching","mastery 5":"Time Warp Tonic","mastery 6":"Minion Dematerializer","max":["Q","E"],"skill Order":["Q","E","Q","W","Q","R","Q","E","Q","E","R","E","E","W"],"victory":false,"blue Side":true,"summ Spell 1":"Flash","summ Spell 2":"Teleport","kda":{"kills":3,"deaths":5,"assists":4},"ccDealt":4021,"wardsKilled":2,"wardsPlaced":8,"csPerMinAt20Mins":6.949999999999999}]},{"name":"Saizo","region":"euw1","matches":[{"champ":"Nocturne","patch":"9.2.","date":1549155957828,"enemy Team":["Sivir","Anivia","Illaoi","Thresh","Rengar"],"ally Team":["Nocturne","Neeko","Janna","Kai'sa","Singed"],"mastery 1":"Lethal Tempo","mastery 2":"Presence of Mind","mastery 3":"Legend: Alacrity","mastery 4":"Coup de Grace","mastery 5":"Transcendence","mastery 6":"Waterwalking","max":["Q","E","W"],"skill Order":["Q","W","E","Q","Q","R","Q","E","Q","E","R","E","E","W","W","R","W"],"victory":false,"blue Side":false,"summ Spell 1":"Smite","summ Spell 2":"Flash","kda":{"kills":11,"deaths":12,"assists":5},"ccDealt":861,"wardsKilled":1,"wardsPlaced":2,"csPerMinAt20Mins":0.5},{"champ":"Kayn","patch":"9.2.","date":1549150225767,"enemy Team":["Renekton",517,"Thresh","Kai'sa","Shyvana"],"ally Team":["Aatrox","Karma","Lucian","Kayn","Orianna"],"mastery 1":"Conqueror","mastery 2":"Triumph","mastery 3":"Legend: Tenacity","mastery 4":"Coup de Grace","mastery 5":"Sudden Impact","mastery 6":"Ravenous Hunter","max":["Q","W","E"],"skill Order":["Q","E","W","Q","Q","R","Q","W","Q","W","R","W","W","E","E","R","E","E"],"victory":true,"blue Side":false,"summ Spell 1":"Smite","summ Spell 2":"Flash","kda":{"kills":7,"deaths":9,"assists":12},"ccDealt":618,"wardsKilled":4,"wardsPlaced":6,"csPerMinAt20Mins":1.55},{"champ":"Kayn","patch":"9.2.","date":1549147945748,"enemy Team":["Irelia","Caitlyn","Sejuani","Wukong","Nami"],"ally Team":["Draven","Kayn","Neeko","Yorick","Pyke"],"mastery 1":"Conqueror","mastery 2":"Triumph","mastery 3":"Legend: Tenacity","mastery 4":"Coup de Grace","mastery 5":"Sudden Impact","mastery 6":"Ravenous Hunter","max":["Q","W"],"skill Order":["Q","E","W","Q","Q","R","Q","W","Q","W","R","W","W","E","E","R"],"victory":true,"blue Side":false,"summ Spell 1":"Smite","summ Spell 2":"Flash","kda":{"kills":7,"deaths":2,"assists":9},"ccDealt":617,"wardsKilled":8,"wardsPlaced":3,"csPerMinAt20Mins":1.2},{"champ":"Graves","patch":"9.2.","date":1549145830019,"enemy Team":["Kayn","LeBlanc","Jhin","Gnar","Thresh"],"ally Team":["Janna","Graves","Lux","Fiora","Sivir"],"mastery 1":"Fleet Footwork","mastery 2":"Triumph","mastery 3":"Legend: Alacrity","mastery 4":"Coup de Grace","mastery 5":"Sudden Impact","mastery 6":"Ravenous Hunter","max":["Q","E"],"skill Order":["E","Q","W","Q","Q","R","Q","E","Q","E","R","E","E","W","W"],"victory":true,"blue Side":true,"summ Spell 1":"Smite","summ Spell 2":"Flash","kda":{"kills":10,"deaths":2,"assists":7},"ccDealt":928,"wardsKilled":5,"wardsPlaced":3,"csPerMinAt20Mins":1.2000000000000002},{"champ":"Kayn","patch":"9.2.","date":1549143520410,"enemy Team":["Lissandra","Aatrox","Sejuani","Zilean","Tristana"],"ally Team":["Tryndamere","Kayn","Malzahar","Vayne","Soraka"],"mastery 1":"Conqueror","mastery 2":"Triumph","mastery 3":"Legend: Tenacity","mastery 4":"Coup de Grace","mastery 5":"Sudden Impact","mastery 6":"Ravenous Hunter","max":["Q","W"],"skill Order":["Q","E","W","Q","Q","R","Q","W","Q","W","R","W","W"],"victory":false,"blue Side":true,"summ Spell 1":"Smite","summ Spell 2":"Flash","kda":{"kills":4,"deaths":6,"assists":3},"ccDealt":681,"wardsKilled":5,"wardsPlaced":7,"csPerMinAt20Mins":0.35},{"champ":"Xin Zhao","patch":"9.2.","date":1549137251518,"enemy Team":["Anivia","Nunu","Draven","Leona","Rengar"],"ally Team":["Xin Zhao","Poppy","LeBlanc","Ezreal","Morgana"],"mastery 1":"Fleet Footwork","mastery 2":"Triumph","mastery 3":"Legend: Alacrity","mastery 4":"Coup de Grace","mastery 5":"Sudden Impact","mastery 6":"Ravenous Hunter","max":["W","E"],"skill Order":["E","Q","W","W","W","R","W","E","W","E","R","E","E"],"victory":true,"blue Side":false,"summ Spell 1":"Smite","summ Spell 2":"Flash","kda":{"kills":11,"deaths":1,"assists":4},"ccDealt":523,"wardsKilled":3,"wardsPlaced":8,"csPerMinAt20Mins":1.2},{"champ":"Xin Zhao","patch":"9.2.","date":1549135230673,"enemy Team":["Nami","Kassadin","Rengar","Draven","Poppy"],"ally Team":["Xin Zhao","Yorick","Orianna","Ezreal","Pyke"],"mastery 1":9923,"mastery 2":"Sudden Impact","mastery 3":"Zombie Ward","mastery 4":"Ravenous Hunter","mastery 5":"Triumph","mastery 6":"Legend: Alacrity","max":["W","E"],"skill Order":["E","Q","W","W","W","R","W","E","W","E","R","E"],"victory":true,"blue Side":false,"summ Spell 1":"Smite","summ Spell 2":"Flash","kda":{"kills":5,"deaths":2,"assists":5},"ccDealt":570,"wardsKilled":4,"wardsPlaced":7,"csPerMinAt20Mins":1.3},{"champ":"Nocturne","patch":"9.2.","date":1548986523376,"enemy Team":["Jax","Zac","Leona","Lissandra","Lucian"],"ally Team":["Nocturne","Vayne","Rakan","Cassiopeia","Akali"],"mastery 1":"Lethal Tempo","mastery 2":"Presence of Mind","mastery 3":"Legend: Alacrity","mastery 4":"Coup de Grace","mastery 5":"Transcendence","mastery 6":"Waterwalking","max":["Q","E","W"],"skill Order":["Q","W","E","Q","Q","R","Q","E","Q","E","R","E","E","W","W","R","W","W"],"victory":true,"blue Side":false,"summ Spell 1":"Smite","summ Spell 2":"Flash","kda":{"kills":8,"deaths":9,"assists":24},"ccDealt":886,"wardsKilled":5,"wardsPlaced":6,"csPerMinAt20Mins":1.2},{"champ":"Kayn","patch":"9.2.","date":1548984475783,"enemy Team":["Kassadin","Rengar","Janna","Twitch","Irelia"],"ally Team":["Kayn","Vayne","Alistar","Yasuo","Twisted Fate"],"mastery 1":"Conqueror","mastery 2":"Triumph","mastery 3":"Legend: Tenacity","mastery 4":"Coup de Grace","mastery 5":"Sudden Impact","mastery 6":"Ravenous Hunter","max":["Q","W"],"skill Order":["Q","E","W","Q","Q","R","Q","W","W","Q","R","W","W","E","E"],"victory":true,"blue Side":true,"summ Spell 1":"Smite","summ Spell 2":"Flash","kda":{"kills":13,"deaths":2,"assists":9},"ccDealt":539,"wardsKilled":6,"wardsPlaced":6,"csPerMinAt20Mins":0.25},{"champ":"Kayn","patch":"9.2.","date":1548900897364,"enemy Team":["Kai'sa","Lux","Gangplank","Thresh","Graves"],"ally Team":["Zed","Urgot","Kayn","Brand","Vayne"],"mastery 1":"Conqueror","mastery 2":"Triumph","mastery 3":"Legend: Tenacity","mastery 4":"Coup de Grace","mastery 5":"Sudden Impact","mastery 6":"Ravenous Hunter","max":["Q","W"],"skill Order":["Q","E","W","Q","Q","R","Q","W","Q","W","R","W","W","E","E","R"],"victory":true,"blue Side":true,"summ Spell 1":"Smite","summ Spell 2":"Flash","kda":{"kills":6,"deaths":1,"assists":9},"ccDealt":767,"wardsKilled":5,"wardsPlaced":4,"csPerMinAt20Mins":0.6000000000000001},{"champ":"Kha'Zix","patch":"9.2.","date":1548850347537,"enemy Team":["Tryndamere","Xin Zhao","Jinx","Ahri","Lulu"],"ally Team":["Kha'Zix","Caitlyn","Thresh","Sion","Zoe"],"mastery 1":"Electrocute","mastery 2":"Sudden Impact","mastery 3":"Eyeball Collection","mastery 4":"Ravenous Hunter","mastery 5":"Triumph","mastery 6":"Legend: Alacrity","max":["Q","W"],"skill Order":["Q","W","E","Q","Q","R","Q","Q","W","Q","W","R","R","W","W","E","E"],"victory":false,"blue Side":true,"summ Spell 1":"Smite","summ Spell 2":"Flash","kda":{"kills":9,"deaths":5,"assists":7},"ccDealt":491,"wardsKilled":5,"wardsPlaced":2,"csPerMinAt20Mins":1.3499999999999999},{"champ":"Kayn","patch":"9.2.","date":1548719742516,"enemy Team":["Lee Sin","Kai'sa","Alistar","Heimerdinger","Jax"],"ally Team":["Kayn","Orianna","Jinx","Fiddlesticks","Swain"],"mastery 1":"Conqueror","mastery 2":"Triumph","mastery 3":"Legend: Tenacity","mastery 4":"Coup de Grace","mastery 5":"Sudden Impact","mastery 6":"Ravenous Hunter","max":["Q","W","E"],"skill Order":["Q","E","W","Q","Q","R","Q","W","Q","W","R","W","W","E","E","R","E","E"],"victory":false,"blue Side":true,"summ Spell 1":"Smite","summ Spell 2":"Flash","kda":{"kills":13,"deaths":10,"assists":12},"ccDealt":5500,"wardsKilled":8,"wardsPlaced":5,"csPerMinAt20Mins":0.7},{"champ":"Kha'Zix","patch":"9.2.","date":1548717474075,"enemy Team":["Nocturne","Leona","Caitlyn","Zed","Illaoi"],"ally Team":["Jhin","Syndra","Kha'Zix","Heimerdinger","Pyke"],"mastery 1":"Electrocute","mastery 2":"Sudden Impact","mastery 3":"Eyeball Collection","mastery 4":"Ravenous Hunter","mastery 5":"Triumph","mastery 6":"Legend: Alacrity","max":["Q","W"],"skill Order":["Q","W","E","Q","Q","R","Q","Q","W","Q","W","R","R","W","W","E"],"victory":false,"blue Side":false,"summ Spell 1":"Smite","summ Spell 2":"Flash","kda":{"kills":7,"deaths":4,"assists":5},"ccDealt":453,"wardsKilled":8,"wardsPlaced":3,"csPerMinAt20Mins":0.65},{"champ":"Kayn","patch":"9.2.","date":1548636644662,"enemy Team":["Kha'Zix","Urgot","Swain","Draven","Soraka"],"ally Team":["Quinn","Riven","Pyke","Kayn","Neeko"],"mastery 1":"Conqueror","mastery 2":"Triumph","mastery 3":"Legend: Tenacity","mastery 4":"Coup de Grace","mastery 5":"Sudden Impact","mastery 6":"Ravenous Hunter","max":["Q","W"],"skill Order":["Q","W","E","Q","Q","R","Q","W","Q","W","R","W","W","E","E","R"],"victory":false,"blue Side":false,"summ Spell 1":"Smite","summ Spell 2":"Flash","kda":{"kills":9,"deaths":3,"assists":14},"ccDealt":700,"wardsKilled":6,"wardsPlaced":1,"csPerMinAt20Mins":1.05},{"champ":"Kha'Zix","patch":"9.2.","date":1548634406821,"enemy Team":["Wukong","Evelynn","Leona","Vayne","Jayce"],"ally Team":["Kha'Zix","Neeko","Camille","Jhin","Taric"],"mastery 1":"Electrocute","mastery 2":"Sudden Impact","mastery 3":"Zombie Ward","mastery 4":"Ravenous Hunter","mastery 5":"Triumph","mastery 6":"Legend: Alacrity","max":["Q","W"],"skill Order":["Q","W","E","Q","Q","R","Q","Q","W","Q","W","R","W","W","W","E"],"victory":false,"blue Side":true,"summ Spell 1":"Smite","summ Spell 2":"Flash","kda":{"kills":7,"deaths":4,"assists":10},"ccDealt":409,"wardsKilled":11,"wardsPlaced":21,"csPerMinAt20Mins":0.4},{"champ":"Graves","patch":"9.2.","date":1548631872878,"enemy Team":["Morgana","Jhin","Wukong","Nidalee","Cassiopeia"],"ally Team":["Jax","Kai'sa","Graves","Neeko","Vel'Koz"],"mastery 1":"Fleet Footwork","mastery 2":"Triumph","mastery 3":"Legend: Alacrity","mastery 4":"Coup de Grace","mastery 5":"Sudden Impact","mastery 6":"Ravenous Hunter","max":["Q","E","W"],"skill Order":["E","Q","W","Q","Q","R","Q","E","Q","E","R","E","E","W","W","R","W","W"],"victory":true,"blue Side":true,"summ Spell 1":"Smite","summ Spell 2":"Flash","kda":{"kills":9,"deaths":2,"assists":6},"ccDealt":1111,"wardsKilled":8,"wardsPlaced":2,"csPerMinAt20Mins":2.6},{"champ":"Xin Zhao","patch":"9.2.","date":1548628847988,"enemy Team":["Lucian","Warwick","Cassiopeia","Nami","Kennen"],"ally Team":["Vayne","Alistar","Lux","Xin Zhao","Yorick"],"mastery 1":9923,"mastery 2":"Sudden Impact","mastery 3":"Eyeball Collection","mastery 4":"Ravenous Hunter","mastery 5":"Triumph","mastery 6":"Legend: Alacrity","max":["W","E","Q"],"skill Order":["E","Q","W","W","W","R","W","E","W","E","R","E","E","Q","Q","R","Q"],"victory":false,"blue Side":true,"summ Spell 1":"Smite","summ Spell 2":"Flash","kda":{"kills":2,"deaths":11,"assists":3},"ccDealt":853,"wardsKilled":6,"wardsPlaced":4,"csPerMinAt20Mins":1},{"champ":"Karthus","patch":"9.2.","date":1548463627040,"enemy Team":["Cassiopeia","Zed","Bard","Jhin","Ivern"],"ally Team":["Tryndamere","Kai'sa","Janna","Karthus","Ziggs"],"mastery 1":"Dark Harvest","mastery 2":"Taste of Blood","mastery 3":"Eyeball Collection","mastery 4":8106,"mastery 5":"Coup de Grace","mastery 6":"Presence of Mind","max":["Q","E","W"],"skill Order":["Q","E","W","Q","Q","R","Q","E","Q","E","R","E","E","W","W","R","W","W"],"victory":true,"blue Side":true,"summ Spell 1":"Smite","summ Spell 2":"Flash","kda":{"kills":7,"deaths":5,"assists":10},"ccDealt":446,"wardsKilled":9,"wardsPlaced":4,"csPerMinAt20Mins":0.75},{"champ":"Kayn","patch":"9.2.","date":1548459612377,"enemy Team":["Sona","Vladimir","Zed","Kai'sa","Rengar"],"ally Team":["Heimerdinger","Kayn","Poppy","Vayne","Nami"],"mastery 1":"Conqueror","mastery 2":"Triumph","mastery 3":"Legend: Tenacity","mastery 4":"Coup de Grace","mastery 5":"Sudden Impact","mastery 6":"Ravenous Hunter","max":["Q","W","E"],"skill Order":["Q","W","E","Q","Q","R","Q","W","Q","W","R","W","W","E","E","R","E","E"],"victory":true,"blue Side":false,"summ Spell 1":"Smite","summ Spell 2":"Flash","kda":{"kills":16,"deaths":4,"assists":7},"ccDealt":651,"wardsKilled":4,"wardsPlaced":4,"csPerMinAt20Mins":1.25},{"champ":"Jax","patch":"8.24","date":1544007783005,"enemy Team":["Viktor","Kha'Zix","Ziggs","Ryze","Janna"],"ally Team":["Renekton","Jax","Lucian","Garen","Camille"],"mastery 1":"Press the Attack","mastery 2":"Triumph","mastery 3":"Legend: Alacrity","mastery 4":"Coup de Grace","mastery 5":"Sudden Impact","mastery 6":"Ravenous Hunter","max":["W","Q"],"skill Order":["E","Q","W","W","W","R","W","Q","W","Q","R","Q","Q","E","E","R"],"victory":true,"blue Side":true,"summ Spell 1":"Smite","summ Spell 2":"Flash","kda":{"kills":7,"deaths":1,"assists":3},"ccDealt":748,"wardsKilled":2,"wardsPlaced":10,"csPerMinAt20Mins":1.25}]},{"name":"Kalwerd","region":"euw1","matches":[{"champ":"LeBlanc","patch":"9.2.","date":1549305473151,"enemy Team":["Sion","Kha'Zix","Fiddlesticks","Jhin","Vayne"],"ally Team":["Sejuani","LeBlanc",517,"Vi","Lucian"],"mastery 1":"Electrocute","mastery 2":"Sudden Impact","mastery 3":"Eyeball Collection","mastery 4":"Ravenous Hunter","mastery 5":"Manaflow Band","mastery 6":"Transcendence","max":["W","Q"],"skill Order":["W","Q","E","W","W","R","W","Q","W","Q","R","Q","Q","E","E","R"],"victory":false,"blue Side":true,"summ Spell 1":"Flash","summ Spell 2":"Ignite","kda":{"kills":12,"deaths":4,"assists":3},"ccDealt":57,"wardsKilled":2,"wardsPlaced":9,"csPerMinAt20Mins":6.4},{"champ":"Viktor","patch":"9.2.","date":1549131753252,"enemy Team":["Ezreal","Tahm Kench","Riven","Nidalee","Olaf"],"ally Team":["Thresh","Lissandra","Fiddlesticks","Viktor","Kai'sa"],"mastery 1":"Phase Rush","mastery 2":"Manaflow Band","mastery 3":"Transcendence","mastery 4":"Scorch","mastery 5":8401,"mastery 6":"Bone Plating","max":["E","Q","W"],"skill Order":["Q","E","E","W","E","R","E","E","Q","Q","E","Q","R","W","Q","Q","W","W","R","W","W"],"victory":true,"blue Side":true,"summ Spell 1":"Flash","summ Spell 2":"Teleport","kda":{"kills":8,"deaths":5,"assists":6},"ccDealt":111,"wardsKilled":3,"wardsPlaced":11,"csPerMinAt20Mins":7.95},{"champ":"Galio","patch":"9.2.","date":1549037815309,"enemy Team":["Janna","Sejuani","Ezreal","Vayne","Jax"],"ally Team":["Rengar","Kai'sa","Galio","Karma","Hecarim"],"mastery 1":"Aftershock","mastery 2":8401,"mastery 3":"Bone Plating","mastery 4":"Overgrowth","mastery 5":"Manaflow Band","mastery 6":"Transcendence","max":["Q","W"],"skill Order":["Q","E","W","Q","Q","R","Q","W","Q","W","R","W"],"victory":true,"blue Side":true,"summ Spell 1":"Flash","summ Spell 2":"Ignite","kda":{"kills":8,"deaths":4,"assists":8},"ccDealt":83,"wardsKilled":1,"wardsPlaced":7,"csPerMinAt20Mins":4.55},{"champ":"LeBlanc","patch":"9.2.","date":1549031115762,"enemy Team":["Urgot","Soraka","Evelynn","Jayce","Vayne"],"ally Team":["LeBlanc","Riven","Karthus","Thresh","Draven"],"mastery 1":"Electrocute","mastery 2":"Sudden Impact","mastery 3":"Eyeball Collection","mastery 4":"Ravenous Hunter","mastery 5":"Manaflow Band","mastery 6":"Transcendence","max":["W","Q"],"skill Order":["W","Q","E","W","W","R","W","Q","W","Q","R","Q","Q","E","E"],"victory":true,"blue Side":false,"summ Spell 1":"Flash","summ Spell 2":"Ignite","kda":{"kills":10,"deaths":2,"assists":9},"ccDealt":76,"wardsKilled":4,"wardsPlaced":12,"csPerMinAt20Mins":7.95},{"champ":"Vladimir","patch":"9.2.","date":1548982168617,"enemy Team":["Ahri","Zyra","Camille","Tryndamere","Ezreal"],"ally Team":["Heimerdinger","Vladimir","Kai'sa","Pyke","Evelynn"],"mastery 1":"Phase Rush","mastery 2":"Shield Bash","mastery 3":"Transcendence","mastery 4":"Scorch","mastery 5":"Cosmic Insight","mastery 6":"Minion Dematerializer","max":["Q","E"],"skill Order":["Q","E","W","Q","Q","R","Q","E","Q","E","R","E","E","W","W","R"],"victory":true,"blue Side":false,"summ Spell 1":"Flash","summ Spell 2":"Ignite","kda":{"kills":6,"deaths":1,"assists":3},"ccDealt":119,"wardsKilled":2,"wardsPlaced":9,"csPerMinAt20Mins":9.1},{"champ":"Irelia","patch":"9.2.","date":1548979704054,"enemy Team":["Lee Sin","Nasus","Vladimir","Karma","Lucian"],"ally Team":["Kennen","Zyra","Irelia","Cassiopeia","Evelynn"],"mastery 1":"Conqueror","mastery 2":"Triumph","mastery 3":"Legend: Alacrity","mastery 4":"Coup de Grace","mastery 5":"Biscuit Delivery","mastery 6":"Time Warp Tonic","max":["Q","E"],"skill Order":["Q","E","W","Q","Q","R","Q","E","Q","E","R","E","E","W","W"],"victory":false,"blue Side":true,"summ Spell 1":"Flash","summ Spell 2":"Ignite","kda":{"kills":3,"deaths":7,"assists":7},"ccDealt":59,"wardsKilled":2,"wardsPlaced":11,"csPerMinAt20Mins":6.85},{"champ":"Viktor","patch":"9.2.","date":1548971112440,"enemy Team":["Morgana","Sejuani","Camille","Galio","Kai'sa"],"ally Team":["Viktor","Kayn","Draven","Yasuo","Karma"],"mastery 1":"Summon Aery","mastery 2":"Manaflow Band","mastery 3":"Transcendence","mastery 4":"Scorch","mastery 5":8401,"mastery 6":"Bone Plating","max":["E","Q","W"],"skill Order":["Q","E","E","W","E","E","R","E","Q","E","Q","Q","R","W","Q","Q","W","W"],"victory":false,"blue Side":true,"summ Spell 1":"Flash","summ Spell 2":"Teleport","kda":{"kills":5,"deaths":5,"assists":4},"ccDealt":147,"wardsKilled":1,"wardsPlaced":13,"csPerMinAt20Mins":5.949999999999999},{"champ":"Galio","patch":"9.2.","date":1548969124884,"enemy Team":["Kha'Zix","Ryze","Caitlyn","Thresh","Ekko"],"ally Team":["Teemo","Alistar","Galio","Kai'sa","Lee Sin"],"mastery 1":"Aftershock","mastery 2":8401,"mastery 3":"Bone Plating","mastery 4":"Unflinching","mastery 5":"Manaflow Band","mastery 6":"Transcendence","max":["Q","W"],"skill Order":["Q","W","E","Q","Q","R","Q","W","Q","W","R","W","W","E"],"victory":true,"blue Side":true,"summ Spell 1":"Flash","summ Spell 2":"Teleport","kda":{"kills":6,"deaths":2,"assists":9},"ccDealt":139,"wardsKilled":0,"wardsPlaced":8,"csPerMinAt20Mins":7.25},{"champ":"Irelia","patch":"9.2.","date":1548957376718,"enemy Team":["Sona","Volibear","Kai'sa","LeBlanc","Viktor"],"ally Team":["Cho'Gath","Swain","Aatrox","Irelia","Lee Sin"],"mastery 1":"Conqueror","mastery 2":"Triumph","mastery 3":"Legend: Bloodline","mastery 4":"Coup de Grace","mastery 5":"Time Warp Tonic","mastery 6":"Biscuit Delivery","max":["Q","E","W"],"skill Order":["Q","E","W","Q","Q","R","Q","E","Q","E","R","E","E","W","W","R","W","W"],"victory":false,"blue Side":false,"summ Spell 1":"Flash","summ Spell 2":"Ignite","kda":{"kills":7,"deaths":5,"assists":14},"ccDealt":522,"wardsKilled":4,"wardsPlaced":11,"csPerMinAt20Mins":6.8500000000000005},{"champ":"LeBlanc","patch":"9.2.","date":1548797108615,"enemy Team":["Vladimir","Jarvan IV","Pyke","Draven","Lissandra"],"ally Team":["Vi","LeBlanc","Urgot","Karma","Caitlyn"],"mastery 1":"Electrocute","mastery 2":"Sudden Impact","mastery 3":"Eyeball Collection","mastery 4":"Ravenous Hunter","mastery 5":"Minion Dematerializer","mastery 6":"Magical Footwear","max":["W","Q"],"skill Order":["W","Q","E","W","W","R","W","Q","W","Q","R","Q","Q","E","E"],"victory":true,"blue Side":true,"summ Spell 1":"Flash","summ Spell 2":"Ignite","kda":{"kills":6,"deaths":2,"assists":6},"ccDealt":72,"wardsKilled":5,"wardsPlaced":11,"csPerMinAt20Mins":7.5},{"champ":"Viktor","patch":"9.2.","date":1548794941511,"enemy Team":["Irelia","Zoe","Ezreal","Kindred","Braum"],"ally Team":["Zed","Morgana","Zac","Viktor","Kai'sa"],"mastery 1":"Summon Aery","mastery 2":"Manaflow Band","mastery 3":"Transcendence","mastery 4":"Scorch","mastery 5":"Bone Plating","mastery 6":8401,"max":["E","Q","W"],"skill Order":["Q","E","E","W","E","E","R","E","Q","Q","E","Q","R","W","Q","Q","W","W","R"],"victory":true,"blue Side":true,"summ Spell 1":"Flash","summ Spell 2":"Teleport","kda":{"kills":8,"deaths":5,"assists":9},"ccDealt":141,"wardsKilled":2,"wardsPlaced":7,"csPerMinAt20Mins":8.3},{"champ":"LeBlanc","patch":"9.2.","date":1548777717684,"enemy Team":["Xin Zhao","Jax","Yasuo","Kai'sa","Thresh"],"ally Team":["Poppy","Kayn","Tristana","LeBlanc","Pyke"],"mastery 1":"Electrocute","mastery 2":"Sudden Impact","mastery 3":"Eyeball Collection","mastery 4":"Ravenous Hunter","mastery 5":"Manaflow Band","mastery 6":"Transcendence","max":["W","Q"],"skill Order":["W","Q","E","W","W","R","W","Q","W","Q","R","Q","Q"],"victory":true,"blue Side":false,"summ Spell 1":"Flash","summ Spell 2":"Ignite","kda":{"kills":9,"deaths":0,"assists":1},"ccDealt":16,"wardsKilled":3,"wardsPlaced":6,"csPerMinAt20Mins":6.85},{"champ":"Zoe","patch":"9.2.","date":1548770624225,"enemy Team":["Lee Sin","Kled","Braum","Vayne","Lissandra"],"ally Team":["Zoe","Fiora","Gragas","Xerath","Jhin"],"mastery 1":"Summon Aery","mastery 2":"Manaflow Band","mastery 3":"Transcendence","mastery 4":"Scorch","mastery 5":"Minion Dematerializer","mastery 6":"Magical Footwear","max":["Q","E"],"skill Order":["Q","W","E","Q","Q","R","Q","E","Q","E","R","E","E"],"victory":false,"blue Side":true,"summ Spell 1":"Flash","summ Spell 2":"Cleanse","kda":{"kills":1,"deaths":3,"assists":1},"ccDealt":108,"wardsKilled":2,"wardsPlaced":12,"csPerMinAt20Mins":8.8},{"champ":"LeBlanc","patch":"9.2.","date":1548768336546,"enemy Team":["Kai'sa","Kennen","Nidalee","Alistar","Kled"],"ally Team":["Lee Sin","Fiora","Lucian","LeBlanc","Morgana"],"mastery 1":"Electrocute","mastery 2":"Sudden Impact","mastery 3":"Eyeball Collection","mastery 4":"Ravenous Hunter","mastery 5":"Magical Footwear","mastery 6":"Minion Dematerializer","max":["W","Q"],"skill Order":["W","Q","E","W","W","R","W","Q","W","Q","R","Q","Q","E","E"],"victory":true,"blue Side":true,"summ Spell 1":"Flash","summ Spell 2":"Ignite","kda":{"kills":7,"deaths":2,"assists":9},"ccDealt":20,"wardsKilled":1,"wardsPlaced":10,"csPerMinAt20Mins":6.35},{"champ":"Zoe","patch":"9.2.","date":1548765171047,"enemy Team":["Dr. Mundo","Elise","Jayce","Morgana","Caitlyn"],"ally Team":["Nami","Kai'sa","Rengar","Zoe","Kennen"],"mastery 1":"Summon Aery","mastery 2":"Manaflow Band","mastery 3":"Transcendence","mastery 4":"Scorch","mastery 5":"Minion Dematerializer","mastery 6":"Time Warp Tonic","max":["Q","E"],"skill Order":["Q","E","W","Q","Q","R","Q","E","Q","E","R","E","E","W","W"],"victory":false,"blue Side":true,"summ Spell 1":"Flash","summ Spell 2":"Ignite","kda":{"kills":3,"deaths":4,"assists":6},"ccDealt":145,"wardsKilled":2,"wardsPlaced":12,"csPerMinAt20Mins":6.35},{"champ":"Vladimir","patch":"9.2.","date":1548716188664,"enemy Team":["Lee Sin","Morgana","Ezreal","Cassiopeia",517],"ally Team":["Xerath","Hecarim","Lucian","Xin Zhao","Vladimir"],"mastery 1":"Phase Rush","mastery 2":"Shield Bash","mastery 3":"Transcendence","mastery 4":"Scorch","mastery 5":"Magical Footwear","mastery 6":"Cosmic Insight","max":["Q","E"],"skill Order":["Q","E","W","Q","Q","R","Q","E","Q","E","R","E","E","W"],"victory":true,"blue Side":false,"summ Spell 1":"Flash","summ Spell 2":"Ignite","kda":{"kills":3,"deaths":6,"assists":10},"ccDealt":56,"wardsKilled":2,"wardsPlaced":10,"csPerMinAt20Mins":6.050000000000001},{"champ":"Ryze","patch":"9.2.","date":1548714399515,"enemy Team":["Tahm Kench","Lucian","LeBlanc","Aatrox","Kindred"],"ally Team":["Kha'Zix","Kai'sa","Ryze","Alistar","Urgot"],"mastery 1":"Aftershock","mastery 2":8401,"mastery 3":"Bone Plating","mastery 4":"Overgrowth","mastery 5":"Manaflow Band","mastery 6":"Transcendence","max":["E","Q"],"skill Order":["W","E","Q","Q","Q","R","E","E","E","Q","R","E"],"victory":false,"blue Side":false,"summ Spell 1":"Flash","summ Spell 2":"Teleport","kda":{"kills":1,"deaths":6,"assists":1},"ccDealt":31,"wardsKilled":1,"wardsPlaced":8,"csPerMinAt20Mins":6.9},{"champ":"LeBlanc","patch":"9.2.","date":1548710686257,"enemy Team":["Kai'sa","Gragas","Blitzcrank",517,"Yasuo"],"ally Team":["Kalista","Alistar","LeBlanc","Sejuani","Nidalee"],"mastery 1":"Electrocute","mastery 2":"Sudden Impact","mastery 3":"Eyeball Collection","mastery 4":"Ravenous Hunter","mastery 5":"Manaflow Band","mastery 6":"Transcendence","max":["W","Q"],"skill Order":["W","Q","E","W","W","R","W","Q","W","Q","R","Q","Q","E"],"victory":false,"blue Side":false,"summ Spell 1":"Flash","summ Spell 2":"Ignite","kda":{"kills":4,"deaths":10,"assists":5},"ccDealt":23,"wardsKilled":0,"wardsPlaced":10,"csPerMinAt20Mins":5.1},{"champ":"Zoe","patch":"9.2.","date":1548696582072,"enemy Team":["Shaco","Xerath","Ezreal","Gragas","Sion"],"ally Team":["Sivir","Kennen","Zoe","Ivern","Zilean"],"mastery 1":"Electrocute","mastery 2":"Taste of Blood","mastery 3":"Eyeball Collection","mastery 4":"Ravenous Hunter","mastery 5":"Manaflow Band","mastery 6":"Transcendence","max":["Q","E"],"skill Order":["Q","W","E","Q","Q","R","Q","E","Q","E","R","E","E","W"],"victory":false,"blue Side":false,"summ Spell 1":"Flash","summ Spell 2":"Ignite","kda":{"kills":6,"deaths":7,"assists":1},"ccDealt":258,"wardsKilled":2,"wardsPlaced":14,"csPerMinAt20Mins":8.65},{"champ":"Zoe","patch":"9.2.","date":1548694797700,"enemy Team":["Soraka","Kennen","Kai'sa","Lee Sin","Yasuo"],"ally Team":["Zoe","Ashe","Morgana","Urgot","Nidalee"],"mastery 1":"Electrocute","mastery 2":"Taste of Blood","mastery 3":"Eyeball Collection","mastery 4":"Ravenous Hunter","mastery 5":"Manaflow Band","mastery 6":"Transcendence","max":["Q","W"],"skill Order":["Q","W","E","Q","Q","R","Q","W","Q","W","R","W","W"],"victory":false,"blue Side":true,"summ Spell 1":"Flash","summ Spell 2":"Ignite","kda":{"kills":1,"deaths":5,"assists":6},"ccDealt":134,"wardsKilled":1,"wardsPlaced":7,"csPerMinAt20Mins":6.8999999999999995}]},{"name":"Gould","region":"euw1","matches":[{"champ":"Lucian","patch":"9.2.","date":1549308565126,"enemy Team":["Evelynn","Jarvan IV","Vladimir","Gangplank","Kai'sa"],"ally Team":["Lucian","Teemo","Neeko","Zoe","Nocturne"],"mastery 1":"Press the Attack","mastery 2":"Triumph","mastery 3":"Legend: Alacrity","mastery 4":"Coup de Grace","mastery 5":"Manaflow Band","mastery 6":"Gathering Storm","max":["Q"],"skill Order":["W","E","Q","Q","Q","R","Q","E","Q","E","R"],"victory":false,"blue Side":true,"summ Spell 1":"Flash","summ Spell 2":"Heal","kda":{"kills":4,"deaths":5,"assists":1},"ccDealt":14,"wardsKilled":0,"wardsPlaced":8,"csPerMinAt20Mins":7},{"champ":"Vayne","patch":"9.2.","date":1549305201365,"enemy Team":["Irelia","Shaco","Ezreal","Annie","Soraka"],"ally Team":["Kha'Zix","Vayne","Nami","Gnar","Vladimir"],"mastery 1":9923,"mastery 2":"Taste of Blood","mastery 3":"Eyeball Collection","mastery 4":"Ravenous Hunter","mastery 5":"Legend: Alacrity","mastery 6":"Coup de Grace","max":["Q","W"],"skill Order":["Q","W","E","Q","Q","R","Q","W","Q","W","R","W","W"],"victory":false,"blue Side":true,"summ Spell 1":"Flash","summ Spell 2":"Heal","kda":{"kills":5,"deaths":6,"assists":3},"ccDealt":163,"wardsKilled":3,"wardsPlaced":6,"csPerMinAt20Mins":7.25},{"champ":"Karthus","patch":"9.2.","date":1549301912451,"enemy Team":["Ryze",517,"Jarvan IV","Ezreal","Zyra"],"ally Team":["Xin Zhao","Ahri","Jax","Karthus","Thresh"],"mastery 1":"Dark Harvest","mastery 2":"Taste of Blood","mastery 3":"Eyeball Collection","mastery 4":8106,"mastery 5":"Presence of Mind","mastery 6":"Last Stand","max":["Q","E"],"skill Order":["Q","E","W","Q","Q","R","Q","E","Q","E","R","E","E","W","W","R"],"victory":false,"blue Side":true,"summ Spell 1":"Flash","summ Spell 2":"Teleport","kda":{"kills":10,"deaths":11,"assists":6},"ccDealt":241,"wardsKilled":3,"wardsPlaced":5,"csPerMinAt20Mins":7.05},{"champ":"Vayne","patch":"9.2.","date":1549200610600,"enemy Team":["Wukong","Thresh","Kha'Zix","Zoe","Draven"],"ally Team":["Ivern","Vayne","Nami","Lux","Orn"],"mastery 1":9923,"mastery 2":"Taste of Blood","mastery 3":"Eyeball Collection","mastery 4":"Ravenous Hunter","mastery 5":"Coup de Grace","mastery 6":"Legend: Alacrity","max":["Q"],"skill Order":["Q","W","E","Q","Q","R","Q","W","W","Q","R"],"victory":true,"blue Side":true,"summ Spell 1":"Flash","summ Spell 2":"Heal","kda":{"kills":13,"deaths":1,"assists":1},"ccDealt":237,"wardsKilled":1,"wardsPlaced":5,"csPerMinAt20Mins":7.199999999999999},{"champ":"Vayne","patch":"9.2.","date":1549160335575,"enemy Team":["Cassiopeia","Kayn","Nami","Tristana","Talon"],"ally Team":["Kayle","Orianna","Jarvan IV","Vayne","Janna"],"mastery 1":9923,"mastery 2":"Taste of Blood","mastery 3":"Eyeball Collection","mastery 4":"Ravenous Hunter","mastery 5":"Coup de Grace","mastery 6":"Legend: Alacrity","max":["Q","W","E"],"skill Order":["Q","W","E","Q","Q","R","Q","W","Q","W","R","W","W","E","E","R","E"],"victory":false,"blue Side":true,"summ Spell 1":"Flash","summ Spell 2":"Heal","kda":{"kills":9,"deaths":8,"assists":8},"ccDealt":456,"wardsKilled":5,"wardsPlaced":13,"csPerMinAt20Mins":6.55},{"champ":"Vayne","patch":"9.2.","date":1549157726697,"enemy Team":["Nasus","Draven","Thresh","Neeko","Shaco"],"ally Team":["Sejuani","Olaf","Lulu","Lissandra","Vayne"],"mastery 1":9923,"mastery 2":"Taste of Blood","mastery 3":"Eyeball Collection","mastery 4":"Ravenous Hunter","mastery 5":"Coup de Grace","mastery 6":"Legend: Alacrity","max":["Q","W"],"skill Order":["Q","W","E","Q","Q","R","Q","W","Q","W","R","W","W","E"],"victory":true,"blue Side":false,"summ Spell 1":"Flash","summ Spell 2":"Heal","kda":{"kills":13,"deaths":4,"assists":7},"ccDealt":284,"wardsKilled":5,"wardsPlaced":10,"csPerMinAt20Mins":6.2},{"champ":"Lucian","patch":"9.2.","date":1549153953608,"enemy Team":["Kassadin","Jhin","Zilean","Darius","Shyvana"],"ally Team":["Illaoi","Pyke","Lucian","Cassiopeia","Zac"],"mastery 1":"Press the Attack","mastery 2":"Triumph","mastery 3":"Legend: Alacrity","mastery 4":"Coup de Grace","mastery 5":"Manaflow Band","mastery 6":"Gathering Storm","max":["Q","E","W"],"skill Order":["W","E","Q","Q","Q","R","Q","E","Q","E","R","E","E","W","W","R","W","W"],"victory":false,"blue Side":false,"summ Spell 1":"Flash","summ Spell 2":"Heal","kda":{"kills":11,"deaths":8,"assists":11},"ccDealt":402,"wardsKilled":2,"wardsPlaced":6,"csPerMinAt20Mins":8.149999999999999},{"champ":"Lucian","patch":"9.2.","date":1549133315687,"enemy Team":["Cassiopeia","Rengar","Jinx","Nami","Renekton"],"ally Team":["Elise","Irelia","Morgana","Lucian","Alistar"],"mastery 1":"Press the Attack","mastery 2":"Triumph","mastery 3":"Legend: Alacrity","mastery 4":"Coup de Grace","mastery 5":"Manaflow Band","mastery 6":"Gathering Storm","max":["Q","E"],"skill Order":["W","E","Q","Q","Q","R","Q","E","Q","E","R","E"],"victory":false,"blue Side":true,"summ Spell 1":"Flash","summ Spell 2":"Heal","kda":{"kills":4,"deaths":6,"assists":6},"ccDealt":17,"wardsKilled":3,"wardsPlaced":8,"csPerMinAt20Mins":6.449999999999999},{"champ":"Ezreal","patch":"9.2.","date":1549108206864,"enemy Team":["Vayne",517,"Lee Sin","Veigar","Aatrox"],"ally Team":["Sejuani","Urgot","Ezreal","Sona","Neeko"],"mastery 1":"Kleptomancy","mastery 2":"Magical Footwear","mastery 3":"Biscuit Delivery","mastery 4":"Cosmic Insight","mastery 5":"Transcendence","mastery 6":"Manaflow Band","max":["Q","E"],"skill Order":["Q","E","W","Q","Q","R","Q","E","Q","E","R","E","E"],"victory":false,"blue Side":false,"summ Spell 1":"Flash","summ Spell 2":"Heal","kda":{"kills":1,"deaths":5,"assists":4},"ccDealt":183,"wardsKilled":2,"wardsPlaced":8,"csPerMinAt20Mins":6.05},{"champ":"Draven","patch":"9.2.","date":1549105444885,"enemy Team":["Vayne","Aatrox","Zyra","Sejuani","Riven"],"ally Team":["Ekko","Zac","Janna","Irelia","Draven"],"mastery 1":"Conqueror","mastery 2":"Triumph","mastery 3":"Legend: Alacrity","mastery 4":"Coup de Grace","mastery 5":"Celerity","mastery 6":"Gathering Storm","max":["Q","W"],"skill Order":["Q","W","E","Q","Q","R","Q","W","Q","W","R","W","W","E","E","R"],"victory":false,"blue Side":false,"summ Spell 1":"Flash","summ Spell 2":"Heal","kda":{"kills":2,"deaths":10,"assists":8},"ccDealt":88,"wardsKilled":3,"wardsPlaced":8,"csPerMinAt20Mins":5.85},{"champ":"Ezreal","patch":"9.2.","date":1549073384510,"enemy Team":["Warwick","Lucian","Alistar","Sejuani","Lissandra"],"ally Team":["Cho'Gath","Lee Sin","Ezreal","Akali","Fiddlesticks"],"mastery 1":"Kleptomancy","mastery 2":"Magical Footwear","mastery 3":"Biscuit Delivery","mastery 4":"Cosmic Insight","mastery 5":"Transcendence","mastery 6":"Manaflow Band","max":["Q","E"],"skill Order":["Q","E","W","Q","Q","R","Q","E","Q","R","E","E","E","W","W"],"victory":true,"blue Side":true,"summ Spell 1":"Flash","summ Spell 2":"Heal","kda":{"kills":5,"deaths":8,"assists":15},"ccDealt":592,"wardsKilled":0,"wardsPlaced":11,"csPerMinAt20Mins":4.75},{"champ":"Ezreal","patch":"9.2.","date":1549070995587,"enemy Team":["Pyke","Lee Sin","Yasuo","Tahm Kench","Twitch"],"ally Team":["Ezreal",517,"Braum","Vladimir","Xin Zhao"],"mastery 1":"Kleptomancy","mastery 2":"Magical Footwear","mastery 3":"Biscuit Delivery","mastery 4":"Cosmic Insight","mastery 5":"Transcendence","mastery 6":"Manaflow Band","max":["Q","E","W"],"skill Order":["Q","E","W","Q","Q","R","Q","E","Q","E","R","E","E","W","W","W"],"victory":false,"blue Side":false,"summ Spell 1":"Flash","summ Spell 2":"Heal","kda":{"kills":9,"deaths":7,"assists":14},"ccDealt":709,"wardsKilled":2,"wardsPlaced":9,"csPerMinAt20Mins":6.3},{"champ":"Ezreal","patch":"9.2.","date":1549026903188,"enemy Team":["Miss Fortune","Vladimir","Pyke","Jax","Nasus"],"ally Team":["Camille","Urgot",517,"Kassadin","Ezreal"],"mastery 1":"Kleptomancy","mastery 2":"Magical Footwear","mastery 3":"Biscuit Delivery","mastery 4":"Cosmic Insight","mastery 5":"Transcendence","mastery 6":"Manaflow Band","max":["Q"],"skill Order":["Q","E","W","Q","Q","R","Q","E","Q","E","R"],"victory":false,"blue Side":false,"summ Spell 1":"Flash","summ Spell 2":"Heal","kda":{"kills":1,"deaths":4,"assists":5},"ccDealt":243,"wardsKilled":1,"wardsPlaced":7,"csPerMinAt20Mins":6.449999999999999},{"champ":"Sivir","patch":"9.2.","date":1548972230284,"enemy Team":["Lux","Neeko","Nocturne","Heimerdinger","Vayne"],"ally Team":["Morgana","Urgot","Elise","Sivir","Anivia"],"mastery 1":"Fleet Footwork","mastery 2":"Triumph","mastery 3":"Legend: Alacrity","mastery 4":"Coup de Grace","mastery 5":"Manaflow Band","mastery 6":"Gathering Storm","max":["Q","W","E"],"skill Order":["Q","E","W","Q","Q","R","Q","W","Q","W","R","W","W","E","E","R","E","E"],"victory":true,"blue Side":false,"summ Spell 1":"Flash","summ Spell 2":"Heal","kda":{"kills":10,"deaths":5,"assists":20},"ccDealt":869,"wardsKilled":9,"wardsPlaced":17,"csPerMinAt20Mins":7.199999999999999},{"champ":"Ezreal","patch":"9.2.","date":1548958279301,"enemy Team":["Shen","Kai'sa","Sona","Shaco","Kassadin"],"ally Team":["Janna","Talon","Sejuani","Gnar","Ezreal"],"mastery 1":"Kleptomancy","mastery 2":"Magical Footwear","mastery 3":"Biscuit Delivery","mastery 4":"Cosmic Insight","mastery 5":"Transcendence","mastery 6":"Manaflow Band","max":["Q","E"],"skill Order":["Q","E","W","Q","Q","R","Q","E","Q","E","R","E","E","W"],"victory":true,"blue Side":false,"summ Spell 1":"Flash","summ Spell 2":"Heal","kda":{"kills":4,"deaths":4,"assists":5},"ccDealt":417,"wardsKilled":0,"wardsPlaced":8,"csPerMinAt20Mins":6.85},{"champ":"Ezreal","patch":"9.2.","date":1548951493917,"enemy Team":["Nami","Renekton","Kai'sa","Xin Zhao","LeBlanc"],"ally Team":["Ezreal","Karma",517,"Kassadin","Karthus"],"mastery 1":"Kleptomancy","mastery 2":"Magical Footwear","mastery 3":"Biscuit Delivery","mastery 4":"Cosmic Insight","mastery 5":"Transcendence","mastery 6":"Manaflow Band","max":["Q","E"],"skill Order":["Q","E","W","Q","Q","R","Q","E","Q","E","R","E","E"],"victory":true,"blue Side":true,"summ Spell 1":"Flash","summ Spell 2":"Heal","kda":{"kills":9,"deaths":4,"assists":8},"ccDealt":381,"wardsKilled":0,"wardsPlaced":9,"csPerMinAt20Mins":6.3},{"champ":"Caitlyn","patch":"9.2.","date":1548949567008,"enemy Team":["Lucian","Cho'Gath","Lee Sin","Anivia","Pyke"],"ally Team":["Diana","Morgana","Caitlyn","Nasus","Kha'Zix"],"mastery 1":"Fleet Footwork","mastery 2":"Triumph","mastery 3":"Legend: Alacrity","mastery 4":"Coup de Grace","mastery 5":"Absolute Focus","mastery 6":"Gathering Storm","max":["Q","W"],"skill Order":["Q","E","W","Q","Q","R","Q","W","Q","W","R","W","W"],"victory":true,"blue Side":true,"summ Spell 1":"Flash","summ Spell 2":"Heal","kda":{"kills":8,"deaths":4,"assists":8},"ccDealt":132,"wardsKilled":5,"wardsPlaced":10,"csPerMinAt20Mins":7.6},{"champ":"Lucian","patch":"9.2.","date":1548946954577,"enemy Team":["Alistar","Vel'Koz","Xin Zhao","Kai'sa","Lissandra"],"ally Team":["Braum",517,"Nidalee","Poppy","Lucian"],"mastery 1":"Press the Attack","mastery 2":"Triumph","mastery 3":"Legend: Alacrity","mastery 4":"Coup de Grace","mastery 5":"Manaflow Band","mastery 6":"Gathering Storm","max":["Q","E"],"skill Order":["W","E","Q","Q","Q","R","Q","E","Q","E","R","E","E","W"],"victory":false,"blue Side":false,"summ Spell 1":"Flash","summ Spell 2":"Heal","kda":{"kills":3,"deaths":5,"assists":8},"ccDealt":174,"wardsKilled":4,"wardsPlaced":7,"csPerMinAt20Mins":7.6},{"champ":"Heimerdinger","patch":"9.2.","date":1548944435057,"enemy Team":["Kai'sa","Cassiopeia","Lee Sin","Renekton","Sona"],"ally Team":["Syndra","Graves","Heimerdinger","Alistar","Jayce"],"mastery 1":"Summon Aery","mastery 2":"Manaflow Band","mastery 3":"Absolute Focus","mastery 4":"Scorch","mastery 5":"Taste of Blood","mastery 6":"Ravenous Hunter","max":["W","Q"],"skill Order":["Q","W","E","W","W","R","W","Q","W","Q","R","Q","Q","E","E"],"victory":false,"blue Side":false,"summ Spell 1":"Flash","summ Spell 2":"Heal","kda":{"kills":10,"deaths":7,"assists":5},"ccDealt":287,"wardsKilled":3,"wardsPlaced":7,"csPerMinAt20Mins":5.85},{"champ":"Ezreal","patch":"9.2.","date":1548936628409,"enemy Team":["Malzahar","Xin Zhao","Riven","Tristana","Nami"],"ally Team":["Viktor","Vi","Bard","Kennen","Ezreal"],"mastery 1":"Kleptomancy","mastery 2":"Magical Footwear","mastery 3":"Biscuit Delivery","mastery 4":"Cosmic Insight","mastery 5":"Transcendence","mastery 6":"Manaflow Band","max":["Q","E"],"skill Order":["Q","E","W","Q","Q","R","Q","E","Q","E","R","E","E","W"],"victory":true,"blue Side":false,"summ Spell 1":"Flash","summ Spell 2":"Heal","kda":{"kills":8,"deaths":3,"assists":9},"ccDealt":507,"wardsKilled":4,"wardsPlaced":9,"csPerMinAt20Mins":7.300000000000001}]},{"name":"Daejin","region":"euw1","matches":[{"champ":"Zilean","patch":"9.2.","date":1549238555054,"enemy Team":["Blitzcrank","Kai'sa","Corki","Skarner","Aatrox"],"ally Team":["Vel'Koz","Jayce","Kha'Zix","Zilean","Vayne"],"mastery 1":"Guardian","mastery 2":"Font of Life","mastery 3":"Second Wind","mastery 4":"Revitalize","mastery 5":"Manaflow Band","mastery 6":"Waterwalking","max":["E","W"],"skill Order":["Q","W","E","E","E","R","E","W","E","W","R","W","W"],"victory":true,"blue Side":true,"summ Spell 1":"Flash","summ Spell 2":"Exhaust","kda":{"kills":1,"deaths":4,"assists":15},"ccDealt":45,"wardsKilled":3,"wardsPlaced":25,"csPerMinAt20Mins":0.30000000000000004},{"champ":"Alistar","patch":"9.2.","date":1549145803823,"enemy Team":["Vladimir","Kai'sa","Karma","Kindred",517],"ally Team":["Sion","Corki","Rek'Sai","Alistar","Caitlyn"],"mastery 1":"Aftershock","mastery 2":"Demolish","mastery 3":"Bone Plating","mastery 4":"Overgrowth","mastery 5":"Cosmic Insight","mastery 6":"Biscuit Delivery","max":["Q","W"],"skill Order":["Q","W","E","Q","Q","R","Q","W","Q","W","R","W","W","E"],"victory":true,"blue Side":false,"summ Spell 1":"Flash","summ Spell 2":"Ignite","kda":{"kills":1,"deaths":5,"assists":24},"ccDealt":137,"wardsKilled":2,"wardsPlaced":29,"csPerMinAt20Mins":1.65},{"champ":"Thresh","patch":"9.2.","date":1549143633366,"enemy Team":["Vayne",517,"Jarvan IV","Zoe","Kennen"],"ally Team":["Rek'Sai","Talon","Thresh","Kalista","Olaf"],"mastery 1":"Aftershock","mastery 2":"Demolish","mastery 3":"Bone Plating","mastery 4":"Unflinching","mastery 5":"Hextech Flashtraption","mastery 6":"Cosmic Insight","max":["Q","W"],"skill Order":["E","Q","W","Q","Q","R","Q","W","Q","W","R","W"],"victory":false,"blue Side":false,"summ Spell 1":"Flash","summ Spell 2":"Ignite","kda":{"kills":2,"deaths":7,"assists":15},"ccDealt":336,"wardsKilled":3,"wardsPlaced":26,"csPerMinAt20Mins":0.3},{"champ":"Morgana","patch":"9.2.","date":1549135186105,"enemy Team":["Draven","Thresh","Kassadin","Maokai","Xin Zhao"],"ally Team":["Fiora","Udyr","Morgana","Vayne","Miss Fortune"],"mastery 1":"Guardian","mastery 2":"Demolish","mastery 3":"Bone Plating","mastery 4":"Revitalize","mastery 5":"Perfect Timing","mastery 6":"Cosmic Insight","max":["Q"],"skill Order":["Q","E","W","Q","Q","R","Q","E","Q","E","R"],"victory":false,"blue Side":false,"summ Spell 1":"Flash","summ Spell 2":"Ignite","kda":{"kills":1,"deaths":7,"assists":15},"ccDealt":105,"wardsKilled":4,"wardsPlaced":22,"csPerMinAt20Mins":0.65},{"champ":"Morgana","patch":"9.2.","date":1549102332465,"enemy Team":["Zilean","Kai'sa","LeBlanc","Rek'Sai","Viktor"],"ally Team":["Shyvana","Draven","Morgana","Riven","Cassiopeia"],"mastery 1":"Guardian","mastery 2":"Demolish","mastery 3":"Bone Plating","mastery 4":"Revitalize","mastery 5":"Perfect Timing","mastery 6":"Cosmic Insight","max":["Q","E"],"skill Order":["Q","W","E","Q","Q","R","Q","E","Q","E","R","E","E","W","W"],"victory":true,"blue Side":true,"summ Spell 1":"Flash","summ Spell 2":"Ignite","kda":{"kills":0,"deaths":5,"assists":18},"ccDealt":112,"wardsKilled":11,"wardsPlaced":36,"csPerMinAt20Mins":0.5},{"champ":"Janna","patch":"9.2.","date":1549069254053,"enemy Team":["Kayn","Thresh","Aatrox","Poppy","Draven"],"ally Team":["Kai'sa","Ekko","Vladimir","Janna","Sejuani"],"mastery 1":"Summon Aery","mastery 2":"Manaflow Band","mastery 3":"Celerity","mastery 4":"Waterwalking","mastery 5":"Taste of Blood","mastery 6":"Relentless Hunter","max":["W","E"],"skill Order":["W","Q","E","W","W","R","W","E","W","E","R","E","E","Q"],"victory":true,"blue Side":false,"summ Spell 1":"Flash","summ Spell 2":"Ignite","kda":{"kills":3,"deaths":1,"assists":23},"ccDealt":184,"wardsKilled":9,"wardsPlaced":20,"csPerMinAt20Mins":0.3},{"champ":"Thresh","patch":"9.2.","date":1549063232205,"enemy Team":["Zyra","Sivir","Darius","Karthus","Tryndamere"],"ally Team":["Jayce","Thresh","Ezreal","Elise","Irelia"],"mastery 1":"Aftershock","mastery 2":"Demolish","mastery 3":"Bone Plating","mastery 4":"Unflinching","mastery 5":"Cosmic Insight","mastery 6":"Hextech Flashtraption","max":["Q"],"skill Order":["E","Q","W","Q","Q","R","Q","W","Q"],"victory":false,"blue Side":false,"summ Spell 1":"Flash","summ Spell 2":"Ignite","kda":{"kills":1,"deaths":4,"assists":1},"ccDealt":64,"wardsKilled":0,"wardsPlaced":18,"csPerMinAt20Mins":0.30000000000000004},{"champ":"Zilean","patch":"9.2.","date":1549040862146,"enemy Team":["Pyke","Vladimir","Draven","Xin Zhao","Cassiopeia"],"ally Team":["Rengar","Zoe","Sion","Zilean","Ezreal"],"mastery 1":"Guardian","mastery 2":"Font of Life","mastery 3":"Second Wind","mastery 4":"Revitalize","mastery 5":"Biscuit Delivery","mastery 6":"Cosmic Insight","max":["E","W"],"skill Order":["Q","W","E","E","E","R","E","W","E","W","R","W","W","Q","Q"],"victory":true,"blue Side":false,"summ Spell 1":"Flash","summ Spell 2":"Exhaust","kda":{"kills":1,"deaths":5,"assists":18},"ccDealt":140,"wardsKilled":4,"wardsPlaced":35,"csPerMinAt20Mins":0.35},{"champ":"Braum","patch":"9.2.","date":1549038984582,"enemy Team":["Ezreal","Jayce","Thresh","Cassiopeia","Kha'Zix"],"ally Team":["Yasuo","Braum","Lucian","Ivern","Vladimir"],"mastery 1":"Guardian","mastery 2":"Demolish","mastery 3":"Bone Plating","mastery 4":"Overgrowth","mastery 5":"Hextech Flashtraption","mastery 6":"Minion Dematerializer","max":["Q"],"skill Order":["Q","W","E","Q","Q","R","Q","E","Q","E","R"],"victory":false,"blue Side":true,"summ Spell 1":"Flash","summ Spell 2":"Ignite","kda":{"kills":1,"deaths":4,"assists":9},"ccDealt":204,"wardsKilled":4,"wardsPlaced":19,"csPerMinAt20Mins":1.75},{"champ":"Leona","patch":"9.2.","date":1549017569452,"enemy Team":["Sion","Talon","Karthus","Jinx","Thresh"],"ally Team":["Teemo","Miss Fortune","Cassiopeia","Leona","Kindred"],"mastery 1":"Aftershock","mastery 2":"Demolish","mastery 3":"Second Wind","mastery 4":"Unflinching","mastery 5":"Biscuit Delivery","mastery 6":"Hextech Flashtraption","max":["W","E"],"skill Order":["Q","E","W","W","W","R","W","E","W","E","R","E","E","Q"],"victory":false,"blue Side":true,"summ Spell 1":"Flash","summ Spell 2":"Ignite","kda":{"kills":1,"deaths":5,"assists":12},"ccDealt":69,"wardsKilled":7,"wardsPlaced":34,"csPerMinAt20Mins":1.55},{"champ":"Thresh","patch":"9.2.","date":1548972899570,"enemy Team":["Braum","Caitlyn","Ahri","Aatrox","Kha'Zix"],"ally Team":["Kassadin","Renekton","Nidalee","Thresh","Lucian"],"mastery 1":"Aftershock","mastery 2":"Demolish","mastery 3":"Bone Plating","mastery 4":"Overgrowth","mastery 5":"Biscuit Delivery","mastery 6":"Hextech Flashtraption","max":["Q","W"],"skill Order":["E","Q","W","Q","Q","R","Q","W","Q","W","R","W","W"],"victory":true,"blue Side":true,"summ Spell 1":"Flash","summ Spell 2":"Ignite","kda":{"kills":1,"deaths":1,"assists":13},"ccDealt":126,"wardsKilled":3,"wardsPlaced":21,"csPerMinAt20Mins":1.5},{"champ":"Janna","patch":"9.2.","date":1548963570164,"enemy Team":["Orn","Wukong","Shaco","Lulu","Twitch"],"ally Team":["Jarvan IV","Vladimir","Lucian","Irelia","Janna"],"mastery 1":"Arcane Comet","mastery 2":"Manaflow Band","mastery 3":"Celerity","mastery 4":"Waterwalking","mastery 5":"Taste of Blood","mastery 6":"Relentless Hunter","max":["W","E"],"skill Order":["W","Q","E","W","W","R","W","E","W","E","R","E","E","Q"],"victory":false,"blue Side":true,"summ Spell 1":"Flash","summ Spell 2":"Ignite","kda":{"kills":4,"deaths":7,"assists":16},"ccDealt":162,"wardsKilled":8,"wardsPlaced":46,"csPerMinAt20Mins":0.5},{"champ":"Alistar","patch":"9.2.","date":1548961302146,"enemy Team":["Morgana","Kalista","Kha'Zix","Zoe","Fiora"],"ally Team":["Nasus","Kai'sa","Zilean","Evelynn","Alistar"],"mastery 1":"Aftershock","mastery 2":"Demolish","mastery 3":"Bone Plating","mastery 4":"Overgrowth","mastery 5":"Biscuit Delivery","mastery 6":"Hextech Flashtraption","max":["Q"],"skill Order":["Q","W","E","Q","Q","R","Q","W","Q","W","R"],"victory":false,"blue Side":true,"summ Spell 1":"Flash","summ Spell 2":"Ignite","kda":{"kills":1,"deaths":8,"assists":7},"ccDealt":59,"wardsKilled":1,"wardsPlaced":18,"csPerMinAt20Mins":1.1},{"champ":"Morgana","patch":"9.2.","date":1548958432112,"enemy Team":["Ashe","Twisted Fate","Lulu","Darius","Evelynn"],"ally Team":["Cassiopeia","Teemo","Caitlyn","Kha'Zix","Morgana"],"mastery 1":"Guardian","mastery 2":"Demolish","mastery 3":"Bone Plating","mastery 4":"Revitalize","mastery 5":"Perfect Timing","mastery 6":"Cosmic Insight","max":["Q"],"skill Order":["Q","W","E","Q","Q","R","Q","E","Q","E","R"],"victory":true,"blue Side":true,"summ Spell 1":"Flash","summ Spell 2":"Ignite","kda":{"kills":1,"deaths":4,"assists":17},"ccDealt":49,"wardsKilled":4,"wardsPlaced":19,"csPerMinAt20Mins":0.15000000000000002},{"champ":"Zilean","patch":"9.2.","date":1548956399139,"enemy Team":["Xin Zhao","Vladimir","Sion","Lucian","Thresh"],"ally Team":["Zilean","Vayne","Nocturne","Mordekaiser","Fizz"],"mastery 1":"Guardian","mastery 2":"Font of Life","mastery 3":"Second Wind","mastery 4":"Revitalize","mastery 5":"Manaflow Band","mastery 6":"Transcendence","max":["E"],"skill Order":["Q","W","E","E","E","R","E","W","E","W","R"],"victory":false,"blue Side":false,"summ Spell 1":"Flash","summ Spell 2":"Exhaust","kda":{"kills":1,"deaths":4,"assists":2},"ccDealt":61,"wardsKilled":3,"wardsPlaced":21,"csPerMinAt20Mins":0.2},{"champ":"Thresh","patch":"9.2.","date":1548953486666,"enemy Team":["Soraka","Elise","Irelia","Kog'Maw","Zoe"],"ally Team":["Graves","Thresh","Lissandra","Lucian","Sion"],"mastery 1":"Guardian","mastery 2":"Demolish","mastery 3":"Bone Plating","mastery 4":"Overgrowth","mastery 5":"Biscuit Delivery","mastery 6":"Hextech Flashtraption","max":["Q"],"skill Order":["E","Q","W","Q","Q","R","Q","W","Q","W"],"victory":false,"blue Side":false,"summ Spell 1":"Flash","summ Spell 2":"Ignite","kda":{"kills":1,"deaths":7,"assists":7},"ccDealt":47,"wardsKilled":5,"wardsPlaced":22,"csPerMinAt20Mins":0.2},{"champ":"Zilean","patch":"9.2.","date":1548948259848,"enemy Team":["Sejuani","Jax","Lissandra","Draven","Lulu"],"ally Team":["Zilean","Yorick","Ivern","Kai'sa","Gangplank"],"mastery 1":"Guardian","mastery 2":"Font of Life","mastery 3":"Second Wind","mastery 4":"Revitalize","mastery 5":"Manaflow Band","mastery 6":"Transcendence","max":["E","W"],"skill Order":["Q","W","E","E","E","R","E","W","E","W","R","W","W"],"victory":true,"blue Side":false,"summ Spell 1":"Flash","summ Spell 2":"Exhaust","kda":{"kills":4,"deaths":1,"assists":11},"ccDealt":63,"wardsKilled":8,"wardsPlaced":26,"csPerMinAt20Mins":0.4},{"champ":"Zilean","patch":"9.2.","date":1548943214138,"enemy Team":["Wukong","Kindred","Draven","Lissandra","Taric"],"ally Team":["Jayce","Sejuani","Zilean","Jhin","Katarina"],"mastery 1":"Guardian","mastery 2":"Font of Life","mastery 3":"Second Wind","mastery 4":"Revitalize","mastery 5":"Manaflow Band","mastery 6":"Transcendence","max":["Q","E","W"],"skill Order":["Q","W","E","Q","Q","R","E","Q","E","E","R","E","W","W","W","R","W"],"victory":false,"blue Side":false,"summ Spell 1":"Flash","summ Spell 2":"Exhaust","kda":{"kills":2,"deaths":7,"assists":24},"ccDealt":255,"wardsKilled":5,"wardsPlaced":36,"csPerMinAt20Mins":0.4},{"champ":"Pyke","patch":"9.2.","date":1548940713903,"enemy Team":["Janna","Lucian","Rengar","Sejuani","Xerath"],"ally Team":["Ezreal","Pyke","Zoe","Viktor","Evelynn"],"mastery 1":"Aftershock","mastery 2":"Demolish","mastery 3":"Bone Plating","mastery 4":"Unflinching","mastery 5":"Presence of Mind","mastery 6":"Legend: Tenacity","max":["Q","E"],"skill Order":["Q","E","W","Q","Q","R","Q","E","Q","E","R","E"],"victory":false,"blue Side":false,"summ Spell 1":"Flash","summ Spell 2":"Ignite","kda":{"kills":2,"deaths":8,"assists":4},"ccDealt":122,"wardsKilled":4,"wardsPlaced":35,"csPerMinAt20Mins":1.45},{"champ":"Tahm Kench","patch":"9.2.","date":1548931095497,"enemy Team":["Neeko","Pyke","Kennen","Sivir","Lee Sin"],"ally Team":["Tahm Kench","Nocturne","Ryze","Jayce","Ezreal"],"mastery 1":"Unsealed Spellbook","mastery 2":"Magical Footwear","mastery 3":"Minion Dematerializer","mastery 4":"Cosmic Insight","mastery 5":"Overgrowth","mastery 6":"Second Wind","max":["Q","W"],"skill Order":["Q","W","E","Q","Q","R","Q","W","Q","W","R","W","W","E","E"],"victory":true,"blue Side":true,"summ Spell 1":"Flash","summ Spell 2":"Exhaust","kda":{"kills":0,"deaths":8,"assists":8},"ccDealt":129,"wardsKilled":15,"wardsPlaced":50,"csPerMinAt20Mins":1.9}]},{"name":"Egospeed","region":"euw1","matches":[{"champ":"Shen","patch":"9.2.","date":1549301604404,"enemy Team":["Riven","Soraka","Kha'Zix","Lucian","Cassiopeia"],"ally Team":["Xerath","Lux","Kai'sa","Sejuani","Shen"],"mastery 1":"Grasp of the Undying","mastery 2":8401,"mastery 3":"Bone Plating","mastery 4":"Revitalize","mastery 5":"Triumph","mastery 6":"Legend: Tenacity","max":["Q","E","W"],"skill Order":["Q","E","W","Q","Q","R","Q","E","Q","E","R","E","E","W","W","R","W","W"],"victory":true,"blue Side":false,"summ Spell 1":"Flash","summ Spell 2":"Teleport","kda":{"kills":4,"deaths":4,"assists":16},"ccDealt":440,"wardsKilled":2,"wardsPlaced":16,"csPerMinAt20Mins":6.3},{"champ":"Shen","patch":"9.2.","date":1549299510589,"enemy Team":["Pyke","Rammus","Riven","Vladimir","Ezreal"],"ally Team":["Kai'sa","Kayn","Janna","Diana","Shen"],"mastery 1":"Grasp of the Undying","mastery 2":8401,"mastery 3":"Bone Plating","mastery 4":"Revitalize","mastery 5":"Triumph","mastery 6":"Legend: Tenacity","max":["Q","E"],"skill Order":["Q","E","W","Q","Q","R","Q","E","Q","E","R","E","E"],"victory":false,"blue Side":false,"summ Spell 1":"Flash","summ Spell 2":"Teleport","kda":{"kills":1,"deaths":6,"assists":7},"ccDealt":253,"wardsKilled":2,"wardsPlaced":7,"csPerMinAt20Mins":6.6},{"champ":"Shen","patch":"9.2.","date":1549297547956,"enemy Team":["Janna","Shyvana","Ezreal","Kled","Xerath"],"ally Team":["Cassiopeia","Shen","Bard","Lee Sin","Kai'sa"],"mastery 1":"Grasp of the Undying","mastery 2":8401,"mastery 3":"Bone Plating","mastery 4":"Revitalize","mastery 5":"Triumph","mastery 6":"Legend: Tenacity","max":["Q"],"skill Order":["Q","E","W","Q","Q","R","Q","E","Q","E","R"],"victory":false,"blue Side":true,"summ Spell 1":"Flash","summ Spell 2":"Teleport","kda":{"kills":0,"deaths":3,"assists":5},"ccDealt":183,"wardsKilled":1,"wardsPlaced":6,"csPerMinAt20Mins":4.8},{"champ":"Shen","patch":"9.2.","date":1549295711640,"enemy Team":[517,"Pantheon","Ekko","Ashe","Soraka"],"ally Team":["Bard","Orianna","Kha'Zix","Ezreal","Shen"],"mastery 1":"Grasp of the Undying","mastery 2":8401,"mastery 3":"Bone Plating","mastery 4":"Revitalize","mastery 5":"Triumph","mastery 6":"Legend: Tenacity","max":["Q","E"],"skill Order":["Q","E","W","Q","Q","R","Q","E","Q","E","R","E"],"victory":false,"blue Side":false,"summ Spell 1":"Flash","summ Spell 2":"Teleport","kda":{"kills":4,"deaths":3,"assists":3},"ccDealt":195,"wardsKilled":0,"wardsPlaced":5,"csPerMinAt20Mins":4.15},{"champ":"Shen","patch":"9.2.","date":1549262035822,"enemy Team":["Kha'Zix","Caitlyn","Garen","Sona","Karthus"],"ally Team":["Yasuo",517,"Zyra","Vayne","Shen"],"mastery 1":"Grasp of the Undying","mastery 2":8401,"mastery 3":"Bone Plating","mastery 4":"Revitalize","mastery 5":"Triumph","mastery 6":"Legend: Tenacity","max":["Q","E","W"],"skill Order":["Q","E","W","Q","Q","R","Q","E","Q","E","R","E","E","W","W","R","W","W"],"victory":true,"blue Side":true,"summ Spell 1":"Flash","summ Spell 2":"Teleport","kda":{"kills":14,"deaths":1,"assists":17},"ccDealt":472,"wardsKilled":0,"wardsPlaced":11,"csPerMinAt20Mins":6.8},{"champ":"Shen","patch":"9.2.","date":1549258736347,"enemy Team":["Pyke","Vayne","Volibear","Ekko","Zed"],"ally Team":["Ezreal","Kha'Zix","Twisted Fate","Nami","Shen"],"mastery 1":"Grasp of the Undying","mastery 2":8401,"mastery 3":"Second Wind","mastery 4":"Revitalize","mastery 5":"Triumph","mastery 6":"Legend: Tenacity","max":["Q","E","W"],"skill Order":["Q","E","W","Q","Q","R","Q","E","Q","E","R","E","E","W","W","R","W","W"],"victory":true,"blue Side":false,"summ Spell 1":"Flash","summ Spell 2":"Teleport","kda":{"kills":8,"deaths":4,"assists":20},"ccDealt":353,"wardsKilled":2,"wardsPlaced":15,"csPerMinAt20Mins":5.449999999999999},{"champ":"Shen","patch":"9.2.","date":1549256199285,"enemy Team":["Nocturne","Blitzcrank","Karma","Ekko","Ashe"],"ally Team":["Pyke","Shen","Lucian","Kayn","Aurelion Sol"],"mastery 1":"Grasp of the Undying","mastery 2":8401,"mastery 3":"Bone Plating","mastery 4":"Revitalize","mastery 5":"Triumph","mastery 6":"Legend: Tenacity","max":["Q","E","W"],"skill Order":["Q","E","W","Q","Q","R","Q","E","Q","E","R","E","E","W","W","R","W"],"victory":false,"blue Side":false,"summ Spell 1":"Flash","summ Spell 2":"Teleport","kda":{"kills":3,"deaths":5,"assists":22},"ccDealt":515,"wardsKilled":2,"wardsPlaced":11,"csPerMinAt20Mins":5},{"champ":"Shen","patch":"9.2.","date":1549254328200,"enemy Team":["Jayce","Lulu","Kai'sa","Master Yi",517],"ally Team":["Kha'Zix","Caitlyn","Sona","Malzahar","Shen"],"mastery 1":"Grasp of the Undying","mastery 2":8401,"mastery 3":"Bone Plating","mastery 4":"Revitalize","mastery 5":"Triumph","mastery 6":"Legend: Tenacity","max":["Q","E"],"skill Order":["Q","E","W","Q","Q","R","Q","E","Q","E","R","E"],"victory":false,"blue Side":false,"summ Spell 1":"Flash","summ Spell 2":"Teleport","kda":{"kills":1,"deaths":5,"assists":5},"ccDealt":168,"wardsKilled":0,"wardsPlaced":5,"csPerMinAt20Mins":4.4},{"champ":"Shen","patch":"9.2.","date":1549252361312,"enemy Team":["Master Yi","Soraka","Viktor","Caitlyn","Twisted Fate"],"ally Team":["Shen","Lucian","Morgana","Karthus","Kha'Zix"],"mastery 1":"Grasp of the Undying","mastery 2":8401,"mastery 3":"Bone Plating","mastery 4":"Revitalize","mastery 5":"Triumph","mastery 6":"Legend: Tenacity","max":["Q","E"],"skill Order":["E","Q","W","Q","Q","R","Q","E","Q","E","R","E","E"],"victory":true,"blue Side":true,"summ Spell 1":"Flash","summ Spell 2":"Teleport","kda":{"kills":3,"deaths":2,"assists":12},"ccDealt":227,"wardsKilled":0,"wardsPlaced":7,"csPerMinAt20Mins":6.550000000000001},{"champ":"Shen","patch":"9.2.","date":1549247666264,"enemy Team":["Zyra","Ekko","Vayne","Kha'Zix","Irelia"],"ally Team":["Nidalee","Lulu","Zed","Kai'sa","Shen"],"mastery 1":"Grasp of the Undying","mastery 2":8401,"mastery 3":"Bone Plating","mastery 4":"Revitalize","mastery 5":"Triumph","mastery 6":"Legend: Tenacity","max":["Q","E"],"skill Order":["Q","E","W","Q","Q","R","Q","E","Q","E","R","E","E","W","W","R"],"victory":true,"blue Side":true,"summ Spell 1":"Flash","summ Spell 2":"Teleport","kda":{"kills":8,"deaths":4,"assists":14},"ccDealt":507,"wardsKilled":0,"wardsPlaced":11,"csPerMinAt20Mins":6.050000000000001},{"champ":"Irelia","patch":"9.2.","date":1549238173343,"enemy Team":["Nami","Lucian","Kha'Zix","Tryndamere","Twisted Fate"],"ally Team":["Ezreal","Anivia","Xin Zhao","Pyke","Irelia"],"mastery 1":"Conqueror","mastery 2":"Triumph","mastery 3":"Legend: Alacrity","mastery 4":"Coup de Grace","mastery 5":"Demolish","mastery 6":"Bone Plating","max":["Q","E"],"skill Order":["Q","E","W","Q","Q","R","Q","E","Q","E","R","E","E"],"victory":false,"blue Side":true,"summ Spell 1":"Flash","summ Spell 2":"Teleport","kda":{"kills":3,"deaths":4,"assists":4},"ccDealt":114,"wardsKilled":0,"wardsPlaced":6,"csPerMinAt20Mins":7.9},{"champ":"Irelia","patch":"9.2.","date":1549231750587,"enemy Team":["Katarina","Lucian","Darius","Ezreal","Fiddlesticks"],"ally Team":["Ekko","Leona","Ashe","Shaco","Irelia"],"mastery 1":"Conqueror","mastery 2":"Triumph","mastery 3":"Legend: Alacrity","mastery 4":"Coup de Grace","mastery 5":"Demolish","mastery 6":"Bone Plating","max":["Q","E"],"skill Order":["Q","E","W","Q","Q","R","Q","E","Q","E","R","E","E","W","W","R"],"victory":true,"blue Side":false,"summ Spell 1":"Flash","summ Spell 2":"Teleport","kda":{"kills":3,"deaths":6,"assists":5},"ccDealt":72,"wardsKilled":1,"wardsPlaced":9,"csPerMinAt20Mins":7.300000000000001},{"champ":"Sejuani","patch":"9.2.","date":1549229196386,"enemy Team":["Janna","Zac","Lucian","Tryndamere","LeBlanc"],"ally Team":["Ezreal","Fizz","Shaco","Sejuani","Thresh"],"mastery 1":"Grasp of the Undying","mastery 2":"Demolish","mastery 3":"Bone Plating","mastery 4":"Overgrowth","mastery 5":"Manaflow Band","mastery 6":"Transcendence","max":["W","Q"],"skill Order":["W","Q","E","W","W","R","W","Q","W","Q","R","Q","Q"],"victory":false,"blue Side":false,"summ Spell 1":"Flash","summ Spell 2":"Teleport","kda":{"kills":2,"deaths":8,"assists":8},"ccDealt":239,"wardsKilled":1,"wardsPlaced":4,"csPerMinAt20Mins":5.3},{"champ":"Urgot","patch":"9.2.","date":1549225233230,"enemy Team":["Darius","LeBlanc","Viktor","Taric","Graves"],"ally Team":["Ezreal","Cassiopeia","Shaco","Urgot","Zyra"],"mastery 1":"Unsealed Spellbook","mastery 2":"Perfect Timing","mastery 3":"Minion Dematerializer","mastery 4":"Approach Velocity","mastery 5":"Demolish","mastery 6":"Bone Plating","max":["Q","W"],"skill Order":["Q","W","E","Q","Q","R","Q","W","Q","W","R","W","W","E","E","R"],"victory":false,"blue Side":false,"summ Spell 1":"Flash","summ Spell 2":"Teleport","kda":{"kills":7,"deaths":6,"assists":6},"ccDealt":386,"wardsKilled":0,"wardsPlaced":7,"csPerMinAt20Mins":6.5},{"champ":"Irelia","patch":"9.2.","date":1549084297651,"enemy Team":["Thresh","Jarvan IV","Nasus","Vayne","Ryze"],"ally Team":["Irelia","Kassadin","Taric","Xin Zhao","Lucian"],"mastery 1":"Conqueror","mastery 2":"Triumph","mastery 3":"Legend: Alacrity","mastery 4":"Coup de Grace","mastery 5":"Taste of Blood","mastery 6":"Ravenous Hunter","max":["Q","E","W"],"skill Order":["Q","E","W","Q","Q","R","Q","E","Q","E","E","R","E","W","W","R","W"],"victory":true,"blue Side":false,"summ Spell 1":"Flash","summ Spell 2":"Teleport","kda":{"kills":8,"deaths":1,"assists":8},"ccDealt":99,"wardsKilled":2,"wardsPlaced":10,"csPerMinAt20Mins":9.05},{"champ":"Yasuo","patch":"9.2.","date":1549081466166,"enemy Team":["Sion","Ezreal","Yorick","Braum","Xin Zhao"],"ally Team":["Evelynn","Jayce","Zyra","Yasuo","Kai'sa"],"mastery 1":"Conqueror","mastery 2":"Triumph","mastery 3":"Legend: Alacrity","mastery 4":"Coup de Grace","mastery 5":"Taste of Blood","mastery 6":"Ravenous Hunter","max":["E","Q","W"],"skill Order":["Q","E","W","E","E","R","E","Q","E","Q","R","Q","Q","W","W","R","W","W"],"victory":true,"blue Side":true,"summ Spell 1":"Flash","summ Spell 2":"Teleport","kda":{"kills":5,"deaths":10,"assists":6},"ccDealt":345,"wardsKilled":2,"wardsPlaced":11,"csPerMinAt20Mins":6.75},{"champ":"Sejuani","patch":"9.2.","date":1549044054500,"enemy Team":["Aatrox","Tristana","Zed","Zilean",517],"ally Team":["Sejuani","Ezreal","Morgana","Camille","Akali"],"mastery 1":"Aftershock","mastery 2":"Demolish","mastery 3":"Bone Plating","mastery 4":"Overgrowth","mastery 5":"Manaflow Band","mastery 6":"Transcendence","max":["W","Q"],"skill Order":["W","Q","E","W","W","R","W","Q","W","E","R","Q","Q"],"victory":true,"blue Side":true,"summ Spell 1":"Flash","summ Spell 2":"Teleport","kda":{"kills":1,"deaths":2,"assists":5},"ccDealt":245,"wardsKilled":0,"wardsPlaced":5,"csPerMinAt20Mins":5.35},{"champ":"Jayce","patch":"9.2.","date":1549042200431,"enemy Team":["Camille","Kassadin","Morgana","Caitlyn","Fiora"],"ally Team":["Jayce","Ezreal","Thresh","Ryze","Lee Sin"],"mastery 1":"Summon Aery","mastery 2":"Manaflow Band","mastery 3":"Absolute Focus","mastery 4":"Scorch","mastery 5":"Taste of Blood","mastery 6":"Ravenous Hunter","max":["Q","W"],"skill Order":["Q","E","W","Q","Q","W","Q","W","Q","W","Q","W"],"victory":false,"blue Side":false,"summ Spell 1":"Flash","summ Spell 2":"Teleport","kda":{"kills":4,"deaths":7,"assists":3},"ccDealt":156,"wardsKilled":1,"wardsPlaced":6,"csPerMinAt20Mins":5.1},{"champ":"Irelia","patch":"9.2.","date":1549040173928,"enemy Team":["LeBlanc","Kai'sa","Nidalee","Lulu","Fiora"],"ally Team":["Gragas","Irelia","Lucian","Janna","Soraka"],"mastery 1":"Conqueror","mastery 2":"Triumph","mastery 3":"Legend: Alacrity","mastery 4":"Coup de Grace","mastery 5":"Demolish","mastery 6":"Bone Plating","max":["Q","E"],"skill Order":["Q","E","W","Q","Q","R","Q","E","Q","E","R","E","E","W"],"victory":false,"blue Side":false,"summ Spell 1":"Flash","summ Spell 2":"Teleport","kda":{"kills":6,"deaths":5,"assists":1},"ccDealt":71,"wardsKilled":2,"wardsPlaced":6,"csPerMinAt20Mins":7.15},{"champ":"Irelia","patch":"9.2.","date":1549037413148,"enemy Team":["Brand","LeBlanc","Kai'sa","Zac","Tryndamere"],"ally Team":["Irelia","Lee Sin","Vel'Koz","Lucian","Yasuo"],"mastery 1":"Conqueror","mastery 2":"Triumph","mastery 3":"Legend: Alacrity","mastery 4":"Coup de Grace","mastery 5":"Demolish","mastery 6":"Bone Plating","max":["Q","E"],"skill Order":["Q","E","W","Q","Q","R","Q","E","Q","E","R","E","E","W"],"victory":true,"blue Side":true,"summ Spell 1":"Flash","summ Spell 2":"Teleport","kda":{"kills":3,"deaths":7,"assists":7},"ccDealt":109,"wardsKilled":1,"wardsPlaced":8,"csPerMinAt20Mins":6.85}]},{"name":"TheKat","region":"euw1","matches":[{"champ":"Blitzcrank","patch":"9.2.","date":1549309549820,"enemy Team":["Kha'Zix","Ezreal","Zoe","Riven","Braum"],"ally Team":["Jax","Blitzcrank","Zed","Hecarim","Caitlyn"],"mastery 1":"Aftershock","mastery 2":"Demolish","mastery 3":"Bone Plating","mastery 4":"Unflinching","mastery 5":"Cosmic Insight","mastery 6":"Biscuit Delivery","max":["Q","W"],"skill Order":["Q","E","W","Q","Q","R","Q","W","W","Q","R","W","W","E","E"],"victory":true,"blue Side":true,"summ Spell 1":"Flash","summ Spell 2":"Ignite","kda":{"kills":0,"deaths":6,"assists":21},"ccDealt":242,"wardsKilled":6,"wardsPlaced":46,"csPerMinAt20Mins":0.25},{"champ":"Nami","patch":"9.2.","date":1549305201365,"enemy Team":["Irelia","Shaco","Ezreal","Annie","Soraka"],"ally Team":["Kha'Zix","Vayne","Nami","Gnar","Vladimir"],"mastery 1":"Summon Aery","mastery 2":"Manaflow Band","mastery 3":"Absolute Focus","mastery 4":"Scorch","mastery 5":"Biscuit Delivery","mastery 6":"Cosmic Insight","max":["W","E"],"skill Order":["W","E","Q","W","W","R","W","E","W","E","R","E","E"],"victory":false,"blue Side":true,"summ Spell 1":"Flash","summ Spell 2":"Ignite","kda":{"kills":1,"deaths":9,"assists":13},"ccDealt":67,"wardsKilled":7,"wardsPlaced":34,"csPerMinAt20Mins":0.25},{"champ":"Thresh","patch":"9.2.","date":1549301912451,"enemy Team":["Ryze",517,"Jarvan IV","Ezreal","Zyra"],"ally Team":["Xin Zhao","Ahri","Jax","Karthus","Thresh"],"mastery 1":"Aftershock","mastery 2":"Demolish","mastery 3":"Second Wind","mastery 4":"Unflinching","mastery 5":"Cosmic Insight","mastery 6":"Biscuit Delivery","max":["Q","E"],"skill Order":["E","Q","W","E","E","R","Q","Q","Q","Q","R","W","E","W","E"],"victory":false,"blue Side":true,"summ Spell 1":"Flash","summ Spell 2":"Ignite","kda":{"kills":2,"deaths":6,"assists":15},"ccDealt":50,"wardsKilled":15,"wardsPlaced":50,"csPerMinAt20Mins":0.65},{"champ":"Thresh","patch":"9.2.","date":1549244134489,"enemy Team":["Udyr","Ekko","Blitzcrank","Sion","Ezreal"],"ally Team":["Zed","Elise","Thresh","Lucian","Irelia"],"mastery 1":"Aftershock","mastery 2":"Demolish","mastery 3":"Bone Plating","mastery 4":"Unflinching","mastery 5":"Cosmic Insight","mastery 6":"Minion Dematerializer","max":["Q"],"skill Order":["E","Q","W","E","E","R","Q","Q","Q","Q","R","W"],"victory":false,"blue Side":false,"summ Spell 1":"Flash","summ Spell 2":"Ignite","kda":{"kills":3,"deaths":7,"assists":14},"ccDealt":160,"wardsKilled":4,"wardsPlaced":33,"csPerMinAt20Mins":1.9},{"champ":"Thresh","patch":"9.2.","date":1549242337051,"enemy Team":["Yasuo","Sejuani","Darius","Kai'sa","Nami"],"ally Team":["Thresh","Lucian","Gangplank","Xin Zhao","Akali"],"mastery 1":"Aftershock","mastery 2":"Demolish","mastery 3":"Bone Plating","mastery 4":"Unflinching","mastery 5":"Hextech Flashtraption","mastery 6":"Cosmic Insight","max":["Q"],"skill Order":["E","Q","W","E","E","R","Q","Q","Q","Q","R"],"victory":true,"blue Side":true,"summ Spell 1":"Flash","summ Spell 2":"Ignite","kda":{"kills":2,"deaths":1,"assists":13},"ccDealt":120,"wardsKilled":6,"wardsPlaced":19,"csPerMinAt20Mins":0.7},{"champ":"Vayne","patch":"9.2.","date":1549240576951,"enemy Team":["Zed","Xerath",517,"Elise","Jhin"],"ally Team":["Lissandra","Vayne","Lee Sin","Thresh","Riven"],"mastery 1":"Press the Attack","mastery 2":"Triumph","mastery 3":"Legend: Alacrity","mastery 4":"Coup de Grace","mastery 5":"Taste of Blood","mastery 6":"Ravenous Hunter","max":["W"],"skill Order":["Q","W","E","W","W","R","W","Q","W","Q","R","E"],"victory":false,"blue Side":false,"summ Spell 1":"Flash","summ Spell 2":"Heal","kda":{"kills":8,"deaths":12,"assists":3},"ccDealt":26,"wardsKilled":1,"wardsPlaced":7,"csPerMinAt20Mins":5.1},{"champ":"Pyke","patch":"9.2.","date":1549238173343,"enemy Team":["Nami","Lucian","Kha'Zix","Tryndamere","Twisted Fate"],"ally Team":["Ezreal","Anivia","Xin Zhao","Pyke","Irelia"],"mastery 1":"Aftershock","mastery 2":"Demolish","mastery 3":"Second Wind","mastery 4":"Unflinching","mastery 5":"Presence of Mind","mastery 6":"Legend: Tenacity","max":["Q"],"skill Order":["Q","E","W","Q","Q","R","Q","E","Q","W","R"],"victory":false,"blue Side":true,"summ Spell 1":"Flash","summ Spell 2":"Ignite","kda":{"kills":1,"deaths":4,"assists":4},"ccDealt":76,"wardsKilled":3,"wardsPlaced":20,"csPerMinAt20Mins":1.7},{"champ":"Blitzcrank","patch":"9.2.","date":1549235650068,"enemy Team":["Darius","Tahm Kench","Syndra","Sivir","Kha'Zix"],"ally Team":["Draven","Blitzcrank","Teemo","Fizz","Lee Sin"],"mastery 1":"Aftershock","mastery 2":"Demolish","mastery 3":"Bone Plating","mastery 4":"Unflinching","mastery 5":"Hextech Flashtraption","mastery 6":"Minion Dematerializer","max":["Q","E","W"],"skill Order":["Q","W","E","Q","Q","R","Q","E","Q","E","R","W","E","W","W"],"victory":false,"blue Side":true,"summ Spell 1":"Flash","summ Spell 2":"Ignite","kda":{"kills":2,"deaths":5,"assists":17},"ccDealt":201,"wardsKilled":6,"wardsPlaced":35,"csPerMinAt20Mins":2.4},{"champ":"Fiddlesticks","patch":"9.2.","date":1549233366780,"enemy Team":["Nasus","Fizz","Nami","Kai'sa","Volibear"],"ally Team":["Cassiopeia","Lucian","Jax","Jarvan IV","Fiddlesticks"],"mastery 1":"Aftershock","mastery 2":"Demolish","mastery 3":"Bone Plating","mastery 4":"Unflinching","mastery 5":"Perfect Timing","mastery 6":"Biscuit Delivery","max":["E","Q"],"skill Order":["E","Q","W","E","Q","R","E","Q","E","Q","R","Q","E","W"],"victory":true,"blue Side":true,"summ Spell 1":"Flash","summ Spell 2":"Ignite","kda":{"kills":2,"deaths":6,"assists":13},"ccDealt":298,"wardsKilled":10,"wardsPlaced":49,"csPerMinAt20Mins":0.65},{"champ":"Thresh","patch":"9.2.","date":1549228998928,"enemy Team":["Neeko","Urgot","Sona","Vayne","Kha'Zix"],"ally Team":["Ezreal","Fizz","Camille","Thresh","Lee Sin"],"mastery 1":"Aftershock","mastery 2":"Demolish","mastery 3":"Bone Plating","mastery 4":"Unflinching","mastery 5":"Minion Dematerializer","mastery 6":"Cosmic Insight","max":["Q"],"skill Order":["Q","E","W","E","E","R","Q","Q","Q","Q","R","W"],"victory":false,"blue Side":false,"summ Spell 1":"Flash","summ Spell 2":"Ignite","kda":{"kills":1,"deaths":4,"assists":9},"ccDealt":110,"wardsKilled":11,"wardsPlaced":29,"csPerMinAt20Mins":1.8},{"champ":"Alistar","patch":"9.2.","date":1549226683213,"enemy Team":["Kai'sa","Ahri","Yasuo","Elise","Leona"],"ally Team":["Alistar","Orianna","Rengar",517,"Sivir"],"mastery 1":"Aftershock","mastery 2":"Demolish","mastery 3":"Bone Plating","mastery 4":"Unflinching","mastery 5":"Hextech Flashtraption","mastery 6":"Minion Dematerializer","max":["Q","W"],"skill Order":["Q","W","E","Q","Q","R","Q","W","Q","W","R","W","W"],"victory":false,"blue Side":true,"summ Spell 1":"Flash","summ Spell 2":"Ignite","kda":{"kills":1,"deaths":8,"assists":12},"ccDealt":151,"wardsKilled":14,"wardsPlaced":48,"csPerMinAt20Mins":1.9},{"champ":"Braum","patch":"9.2.","date":1549224476004,"enemy Team":["Cassiopeia","Lucian","Xin Zhao","Lulu","Akali"],"ally Team":["Braum","Riven","Jarvan IV","Ezreal","Syndra"],"mastery 1":"Guardian","mastery 2":"Font of Life","mastery 3":"Bone Plating","mastery 4":"Unflinching","mastery 5":"Minion Dematerializer","mastery 6":"Approach Velocity","max":["Q","E"],"skill Order":["Q","W","E","Q","Q","R","Q","E","Q","E","R","E","E","W"],"victory":true,"blue Side":false,"summ Spell 1":"Flash","summ Spell 2":"Ignite","kda":{"kills":4,"deaths":3,"assists":19},"ccDealt":203,"wardsKilled":12,"wardsPlaced":36,"csPerMinAt20Mins":2.25},{"champ":"Nami","patch":"9.2.","date":1549200610600,"enemy Team":["Wukong","Thresh","Kha'Zix","Zoe","Draven"],"ally Team":["Ivern","Vayne","Nami","Lux","Orn"],"mastery 1":"Summon Aery","mastery 2":"Manaflow Band","mastery 3":"Absolute Focus","mastery 4":"Scorch","mastery 5":"Second Wind","mastery 6":"Revitalize","max":["W"],"skill Order":["W","E","Q","W","W","R","W","E","W","E"],"victory":true,"blue Side":true,"summ Spell 1":"Flash","summ Spell 2":"Exhaust","kda":{"kills":0,"deaths":3,"assists":15},"ccDealt":96,"wardsKilled":5,"wardsPlaced":19,"csPerMinAt20Mins":0.65},{"champ":"Thresh","patch":"9.2.","date":1549164376459,"enemy Team":["Zoe","Soraka","Ezreal","Kayle","Evelynn"],"ally Team":["Tristana","Lee Sin","Aatrox","Urgot","Thresh"],"mastery 1":"Aftershock","mastery 2":"Demolish","mastery 3":"Bone Plating","mastery 4":"Unflinching","mastery 5":"Minion Dematerializer","mastery 6":"Cosmic Insight","max":["Q"],"skill Order":["Q","E","W","E","E","R","Q","Q","Q","Q"],"victory":false,"blue Side":false,"summ Spell 1":"Flash","summ Spell 2":"Ignite","kda":{"kills":3,"deaths":7,"assists":8},"ccDealt":97,"wardsKilled":9,"wardsPlaced":27,"csPerMinAt20Mins":1.15},{"champ":"Thresh","patch":"9.2.","date":1549161635322,"enemy Team":["Morgana","Riven","Kayn","Tristana","Ahri"],"ally Team":["Sion","Zac","Thresh","Lucian","Lissandra"],"mastery 1":"Aftershock","mastery 2":"Demolish","mastery 3":"Bone Plating","mastery 4":"Unflinching","mastery 5":"Minion Dematerializer","mastery 6":"Cosmic Insight","max":["Q"],"skill Order":["E","Q","W","E","E","R","Q","Q","Q","Q","R","W"],"victory":false,"blue Side":true,"summ Spell 1":"Flash","summ Spell 2":"Ignite","kda":{"kills":6,"deaths":11,"assists":13},"ccDealt":228,"wardsKilled":5,"wardsPlaced":29,"csPerMinAt20Mins":1.3499999999999999},{"champ":"Pyke","patch":"9.2.","date":1549159491916,"enemy Team":["Zyra",517,"Kassadin","Kai'sa","Kindred"],"ally Team":["Lucian","Vladimir","Yasuo","Lee Sin","Pyke"],"mastery 1":"Aftershock","mastery 2":"Demolish","mastery 3":"Second Wind","mastery 4":"Unflinching","mastery 5":"Presence of Mind","mastery 6":"Legend: Tenacity","max":["Q","E"],"skill Order":["Q","E","W","Q","Q","R","Q","E","Q","W","R","E","E"],"victory":false,"blue Side":false,"summ Spell 1":"Flash","summ Spell 2":"Ignite","kda":{"kills":8,"deaths":7,"assists":9},"ccDealt":141,"wardsKilled":6,"wardsPlaced":34,"csPerMinAt20Mins":1.5499999999999998},{"champ":"Thresh","patch":"9.2.","date":1549157461891,"enemy Team":["Vayne","Lux","Pyke","Rengar","Akali"],"ally Team":["Gragas","Thresh","Zoe","Kennen","Ezreal"],"mastery 1":"Aftershock","mastery 2":"Demolish","mastery 3":"Bone Plating","mastery 4":"Unflinching","mastery 5":"Minion Dematerializer","mastery 6":"Cosmic Insight","max":["Q"],"skill Order":["E","Q","W","E","E","R","Q","Q","Q","Q","R","W"],"victory":true,"blue Side":true,"summ Spell 1":"Flash","summ Spell 2":"Ignite","kda":{"kills":2,"deaths":6,"assists":15},"ccDealt":166,"wardsKilled":6,"wardsPlaced":25,"csPerMinAt20Mins":1.6},{"champ":"Pyke","patch":"9.2.","date":1549155233153,"enemy Team":["Blitzcrank","Ezreal","Shaco","Jayce","Vel'Koz"],"ally Team":["Sejuani","Pyke","Yorick","Kai'sa","Malzahar"],"mastery 1":"Aftershock","mastery 2":"Demolish","mastery 3":"Second Wind","mastery 4":"Unflinching","mastery 5":"Presence of Mind","mastery 6":"Legend: Tenacity","max":["Q","E"],"skill Order":["Q","E","W","Q","Q","R","Q","E","Q","E","R","W","E"],"victory":true,"blue Side":false,"summ Spell 1":"Flash","summ Spell 2":"Ignite","kda":{"kills":8,"deaths":3,"assists":7},"ccDealt":103,"wardsKilled":10,"wardsPlaced":29,"csPerMinAt20Mins":1.75},{"champ":"Blitzcrank","patch":"9.2.","date":1549150906949,"enemy Team":["Kha'Zix","Syndra","Malphite","Draven","Zilean"],"ally Team":["Shyvana","Cassiopeia","Lucian","Evelynn","Blitzcrank"],"mastery 1":"Predator","mastery 2":"Sudden Impact","mastery 3":"Ghost Poro","mastery 4":"Ingenious Hunter","mastery 5":"Perfect Timing","mastery 6":"Minion Dematerializer","max":["Q","E"],"skill Order":["Q","E","W","Q","Q","R","Q","E","Q","E","R","E","W","E"],"victory":false,"blue Side":false,"summ Spell 1":"Flash","summ Spell 2":"Ignite","kda":{"kills":2,"deaths":7,"assists":16},"ccDealt":155,"wardsKilled":13,"wardsPlaced":42,"csPerMinAt20Mins":1.65},{"champ":"Thresh","patch":"9.2.","date":1549148713588,"enemy Team":["Kai'sa","Kennen","Jayce","Alistar","Vi"],"ally Team":["Thresh","Lissandra","Elise","Tryndamere","Ezreal"],"mastery 1":"Aftershock","mastery 2":"Demolish","mastery 3":"Second Wind","mastery 4":"Unflinching","mastery 5":"Minion Dematerializer","mastery 6":"Cosmic Insight","max":["Q"],"skill Order":["E","Q","W","E","E","R","Q","Q","Q","Q","R"],"victory":false,"blue Side":true,"summ Spell 1":"Flash","summ Spell 2":"Ignite","kda":{"kills":0,"deaths":5,"assists":12},"ccDealt":112,"wardsKilled":9,"wardsPlaced":42,"csPerMinAt20Mins":1.4}]}]}